[{"arguments":["clang","-Wno-documentation-unknown-command","-Wno-unknown-warning-option","-Wno-unknown-pragmas","-nostdinc","-nostdinc++","-std=gnu++1z","-Wall","-Wextra","-Wextra","-fexceptions","-mthreads","-fsyntax-only","-m64","--target=x86_64-w64-mingw32","-DUNICODE","-D_UNICODE","-DWIN32","-DMINGW_HAS_SECURE_API","-DQT_NO_DEBUG","-DQT_PRINTSUPPORT_LIB","-DQT_CHARTS_LIB","-DQT_OPENGLWIDGETS_LIB","-DQT_WIDGETS_LIB","-DQT_OPENGL_LIB","-DQT_GUI_LIB","-DQT_SQL_LIB","-DQT_CORE_LIB","-DQT_NEEDS_QMAIN","-DQ_CREATOR_RUN","-IC:\\Qt\\Tools\\QtCreator\\share\\qtcreator\\cplusplus\\wrappedMingwHeaders","-IC:\\Qt\\Tools\\QtCreator\\share\\qtcreator\\cplusplus\\wrappedQtHeaders","-IC:\\Qt\\Tools\\QtCreator\\share\\qtcreator\\cplusplus\\wrappedQtHeaders\\QtCore","-ID:\\qt\\qt\\STO2","-IC:\\Qt\\6.4.1\\mingw_64\\include","-IC:\\Qt\\6.4.1\\mingw_64\\include\\QtPrintSupport","-IC:\\Qt\\6.4.1\\mingw_64\\include\\QtCharts","-IC:\\Qt\\6.4.1\\mingw_64\\include\\QtOpenGLWidgets","-IC:\\Qt\\6.4.1\\mingw_64\\include\\QtWidgets","-IC:\\Qt\\6.4.1\\mingw_64\\include\\QtOpenGL","-IC:\\Qt\\6.4.1\\mingw_64\\include\\QtGui","-IC:\\Qt\\6.4.1\\mingw_64\\include\\QtSql","-IC:\\Qt\\6.4.1\\mingw_64\\include\\QtCore","-ID:\\qt\\qt\\STO2\\release","-IC:\\Qt\\6.4.1\\mingw_64\\mkspecs\\win32-g++","-isystem","C:\\Qt\\Tools\\mingw1120_64\\lib\\gcc\\x86_64-w64-mingw32\\11.2.0\\include\\c++","-isystem","C:\\Qt\\Tools\\mingw1120_64\\lib\\gcc\\x86_64-w64-mingw32\\11.2.0\\include\\c++\\x86_64-w64-mingw32","-isystem","C:\\Qt\\Tools\\mingw1120_64\\lib\\gcc\\x86_64-w64-mingw32\\11.2.0\\include\\c++\\backward","-isystem","C:\\Qt\\Tools\\QtCreator\\bin\\clang\\lib\\clang\\15.0.0\\include","-isystem","C:\\Qt\\Tools\\mingw1120_64\\x86_64-w64-mingw32\\include","-fmessage-length=0","-fdiagnostics-show-note-include-stack","-fretain-comments-from-system-headers","-fmacro-backtrace-limit=0","-ferror-limit=1000","-x","c++","D:\\qt\\qt\\STO2\\clientadd.cpp"],"directory":"D:/qt/qt/STO2/.qtc_clangd","file":"D:/qt/qt/STO2/clientadd.cpp"},{"arguments":["clang","-Wno-documentation-unknown-command","-Wno-unknown-warning-option","-Wno-unknown-pragmas","-nostdinc","-nostdinc++","-std=gnu++1z","-Wall","-Wextra","-Wextra","-fexceptions","-mthreads","-fsyntax-only","-m64","--target=x86_64-w64-mingw32","-DUNICODE","-D_UNICODE","-DWIN32","-DMINGW_HAS_SECURE_API","-DQT_NO_DEBUG","-DQT_PRINTSUPPORT_LIB","-DQT_CHARTS_LIB","-DQT_OPENGLWIDGETS_LIB","-DQT_WIDGETS_LIB","-DQT_OPENGL_LIB","-DQT_GUI_LIB","-DQT_SQL_LIB","-DQT_CORE_LIB","-DQT_NEEDS_QMAIN","-DQ_CREATOR_RUN","-IC:\\Qt\\Tools\\QtCreator\\share\\qtcreator\\cplusplus\\wrappedMingwHeaders","-IC:\\Qt\\Tools\\QtCreator\\share\\qtcreator\\cplusplus\\wrappedQtHeaders","-IC:\\Qt\\Tools\\QtCreator\\share\\qtcreator\\cplusplus\\wrappedQtHeaders\\QtCore","-ID:\\qt\\qt\\STO2","-IC:\\Qt\\6.4.1\\mingw_64\\include","-IC:\\Qt\\6.4.1\\mingw_64\\include\\QtPrintSupport","-IC:\\Qt\\6.4.1\\mingw_64\\include\\QtCharts","-IC:\\Qt\\6.4.1\\mingw_64\\include\\QtOpenGLWidgets","-IC:\\Qt\\6.4.1\\mingw_64\\include\\QtWidgets","-IC:\\Qt\\6.4.1\\mingw_64\\include\\QtOpenGL","-IC:\\Qt\\6.4.1\\mingw_64\\include\\QtGui","-IC:\\Qt\\6.4.1\\mingw_64\\include\\QtSql","-IC:\\Qt\\6.4.1\\mingw_64\\include\\QtCore","-ID:\\qt\\qt\\STO2\\release","-IC:\\Qt\\6.4.1\\mingw_64\\mkspecs\\win32-g++","-isystem","C:\\Qt\\Tools\\mingw1120_64\\lib\\gcc\\x86_64-w64-mingw32\\11.2.0\\include\\c++","-isystem","C:\\Qt\\Tools\\mingw1120_64\\lib\\gcc\\x86_64-w64-mingw32\\11.2.0\\include\\c++\\x86_64-w64-mingw32","-isystem","C:\\Qt\\Tools\\mingw1120_64\\lib\\gcc\\x86_64-w64-mingw32\\11.2.0\\include\\c++\\backward","-isystem","C:\\Qt\\Tools\\QtCreator\\bin\\clang\\lib\\clang\\15.0.0\\include","-isystem","C:\\Qt\\Tools\\mingw1120_64\\x86_64-w64-mingw32\\include","-fmessage-length=0","-fdiagnostics-show-note-include-stack","-fretain-comments-from-system-headers","-fmacro-backtrace-limit=0","-ferror-limit=1000","-x","c++","D:\\qt\\qt\\STO2\\infobase.cpp"],"directory":"D:/qt/qt/STO2/.qtc_clangd","file":"D:/qt/qt/STO2/infobase.cpp"},{"arguments":["clang","-Wno-documentation-unknown-command","-Wno-unknown-warning-option","-Wno-unknown-pragmas","-nostdinc","-nostdinc++","-std=gnu++1z","-Wall","-Wextra","-Wextra","-fexceptions","-mthreads","-fsyntax-only","-m64","--target=x86_64-w64-mingw32","-DUNICODE","-D_UNICODE","-DWIN32","-DMINGW_HAS_SECURE_API","-DQT_NO_DEBUG","-DQT_PRINTSUPPORT_LIB","-DQT_CHARTS_LIB","-DQT_OPENGLWIDGETS_LIB","-DQT_WIDGETS_LIB","-DQT_OPENGL_LIB","-DQT_GUI_LIB","-DQT_SQL_LIB","-DQT_CORE_LIB","-DQT_NEEDS_QMAIN","-DQ_CREATOR_RUN","-IC:\\Qt\\Tools\\QtCreator\\share\\qtcreator\\cplusplus\\wrappedMingwHeaders","-IC:\\Qt\\Tools\\QtCreator\\share\\qtcreator\\cplusplus\\wrappedQtHeaders","-IC:\\Qt\\Tools\\QtCreator\\share\\qtcreator\\cplusplus\\wrappedQtHeaders\\QtCore","-ID:\\qt\\qt\\STO2","-IC:\\Qt\\6.4.1\\mingw_64\\include","-IC:\\Qt\\6.4.1\\mingw_64\\include\\QtPrintSupport","-IC:\\Qt\\6.4.1\\mingw_64\\include\\QtCharts","-IC:\\Qt\\6.4.1\\mingw_64\\include\\QtOpenGLWidgets","-IC:\\Qt\\6.4.1\\mingw_64\\include\\QtWidgets","-IC:\\Qt\\6.4.1\\mingw_64\\include\\QtOpenGL","-IC:\\Qt\\6.4.1\\mingw_64\\include\\QtGui","-IC:\\Qt\\6.4.1\\mingw_64\\include\\QtSql","-IC:\\Qt\\6.4.1\\mingw_64\\include\\QtCore","-ID:\\qt\\qt\\STO2\\release","-IC:\\Qt\\6.4.1\\mingw_64\\mkspecs\\win32-g++","-isystem","C:\\Qt\\Tools\\mingw1120_64\\lib\\gcc\\x86_64-w64-mingw32\\11.2.0\\include\\c++","-isystem","C:\\Qt\\Tools\\mingw1120_64\\lib\\gcc\\x86_64-w64-mingw32\\11.2.0\\include\\c++\\x86_64-w64-mingw32","-isystem","C:\\Qt\\Tools\\mingw1120_64\\lib\\gcc\\x86_64-w64-mingw32\\11.2.0\\include\\c++\\backward","-isystem","C:\\Qt\\Tools\\QtCreator\\bin\\clang\\lib\\clang\\15.0.0\\include","-isystem","C:\\Qt\\Tools\\mingw1120_64\\x86_64-w64-mingw32\\include","-fmessage-length=0","-fdiagnostics-show-note-include-stack","-fretain-comments-from-system-headers","-fmacro-backtrace-limit=0","-ferror-limit=1000","-x","c++","D:\\qt\\qt\\STO2\\main.cpp"],"directory":"D:/qt/qt/STO2/.qtc_clangd","file":"D:/qt/qt/STO2/main.cpp"},{"arguments":["clang","-Wno-documentation-unknown-command","-Wno-unknown-warning-option","-Wno-unknown-pragmas","-nostdinc","-nostdinc++","-std=gnu++1z","-Wall","-Wextra","-Wextra","-fexceptions","-mthreads","-fsyntax-only","-m64","--target=x86_64-w64-mingw32","-DUNICODE","-D_UNICODE","-DWIN32","-DMINGW_HAS_SECURE_API","-DQT_NO_DEBUG","-DQT_PRINTSUPPORT_LIB","-DQT_CHARTS_LIB","-DQT_OPENGLWIDGETS_LIB","-DQT_WIDGETS_LIB","-DQT_OPENGL_LIB","-DQT_GUI_LIB","-DQT_SQL_LIB","-DQT_CORE_LIB","-DQT_NEEDS_QMAIN","-DQ_CREATOR_RUN","-IC:\\Qt\\Tools\\QtCreator\\share\\qtcreator\\cplusplus\\wrappedMingwHeaders","-IC:\\Qt\\Tools\\QtCreator\\share\\qtcreator\\cplusplus\\wrappedQtHeaders","-IC:\\Qt\\Tools\\QtCreator\\share\\qtcreator\\cplusplus\\wrappedQtHeaders\\QtCore","-ID:\\qt\\qt\\STO2","-IC:\\Qt\\6.4.1\\mingw_64\\include","-IC:\\Qt\\6.4.1\\mingw_64\\include\\QtPrintSupport","-IC:\\Qt\\6.4.1\\mingw_64\\include\\QtCharts","-IC:\\Qt\\6.4.1\\mingw_64\\include\\QtOpenGLWidgets","-IC:\\Qt\\6.4.1\\mingw_64\\include\\QtWidgets","-IC:\\Qt\\6.4.1\\mingw_64\\include\\QtOpenGL","-IC:\\Qt\\6.4.1\\mingw_64\\include\\QtGui","-IC:\\Qt\\6.4.1\\mingw_64\\include\\QtSql","-IC:\\Qt\\6.4.1\\mingw_64\\include\\QtCore","-ID:\\qt\\qt\\STO2\\release","-IC:\\Qt\\6.4.1\\mingw_64\\mkspecs\\win32-g++","-isystem","C:\\Qt\\Tools\\mingw1120_64\\lib\\gcc\\x86_64-w64-mingw32\\11.2.0\\include\\c++","-isystem","C:\\Qt\\Tools\\mingw1120_64\\lib\\gcc\\x86_64-w64-mingw32\\11.2.0\\include\\c++\\x86_64-w64-mingw32","-isystem","C:\\Qt\\Tools\\mingw1120_64\\lib\\gcc\\x86_64-w64-mingw32\\11.2.0\\include\\c++\\backward","-isystem","C:\\Qt\\Tools\\QtCreator\\bin\\clang\\lib\\clang\\15.0.0\\include","-isystem","C:\\Qt\\Tools\\mingw1120_64\\x86_64-w64-mingw32\\include","-fmessage-length=0","-fdiagnostics-show-note-include-stack","-fretain-comments-from-system-headers","-fmacro-backtrace-limit=0","-ferror-limit=1000","-x","c++","D:\\qt\\qt\\STO2\\mainwindow.cpp"],"directory":"D:/qt/qt/STO2/.qtc_clangd","file":"D:/qt/qt/STO2/mainwindow.cpp"},{"arguments":["clang","-Wno-documentation-unknown-command","-Wno-unknown-warning-option","-Wno-unknown-pragmas","-nostdinc","-nostdinc++","-std=gnu++1z","-Wall","-Wextra","-Wextra","-fexceptions","-mthreads","-fsyntax-only","-m64","--target=x86_64-w64-mingw32","-DUNICODE","-D_UNICODE","-DWIN32","-DMINGW_HAS_SECURE_API","-DQT_NO_DEBUG","-DQT_PRINTSUPPORT_LIB","-DQT_CHARTS_LIB","-DQT_OPENGLWIDGETS_LIB","-DQT_WIDGETS_LIB","-DQT_OPENGL_LIB","-DQT_GUI_LIB","-DQT_SQL_LIB","-DQT_CORE_LIB","-DQT_NEEDS_QMAIN","-DQ_CREATOR_RUN","-IC:\\Qt\\Tools\\QtCreator\\share\\qtcreator\\cplusplus\\wrappedMingwHeaders","-IC:\\Qt\\Tools\\QtCreator\\share\\qtcreator\\cplusplus\\wrappedQtHeaders","-IC:\\Qt\\Tools\\QtCreator\\share\\qtcreator\\cplusplus\\wrappedQtHeaders\\QtCore","-ID:\\qt\\qt\\STO2","-IC:\\Qt\\6.4.1\\mingw_64\\include","-IC:\\Qt\\6.4.1\\mingw_64\\include\\QtPrintSupport","-IC:\\Qt\\6.4.1\\mingw_64\\include\\QtCharts","-IC:\\Qt\\6.4.1\\mingw_64\\include\\QtOpenGLWidgets","-IC:\\Qt\\6.4.1\\mingw_64\\include\\QtWidgets","-IC:\\Qt\\6.4.1\\mingw_64\\include\\QtOpenGL","-IC:\\Qt\\6.4.1\\mingw_64\\include\\QtGui","-IC:\\Qt\\6.4.1\\mingw_64\\include\\QtSql","-IC:\\Qt\\6.4.1\\mingw_64\\include\\QtCore","-ID:\\qt\\qt\\STO2\\release","-IC:\\Qt\\6.4.1\\mingw_64\\mkspecs\\win32-g++","-isystem","C:\\Qt\\Tools\\mingw1120_64\\lib\\gcc\\x86_64-w64-mingw32\\11.2.0\\include\\c++","-isystem","C:\\Qt\\Tools\\mingw1120_64\\lib\\gcc\\x86_64-w64-mingw32\\11.2.0\\include\\c++\\x86_64-w64-mingw32","-isystem","C:\\Qt\\Tools\\mingw1120_64\\lib\\gcc\\x86_64-w64-mingw32\\11.2.0\\include\\c++\\backward","-isystem","C:\\Qt\\Tools\\QtCreator\\bin\\clang\\lib\\clang\\15.0.0\\include","-isystem","C:\\Qt\\Tools\\mingw1120_64\\x86_64-w64-mingw32\\include","-fmessage-length=0","-fdiagnostics-show-note-include-stack","-fretain-comments-from-system-headers","-fmacro-backtrace-limit=0","-ferror-limit=1000","-x","c++","D:\\qt\\qt\\STO2\\ordersadd.cpp"],"directory":"D:/qt/qt/STO2/.qtc_clangd","file":"D:/qt/qt/STO2/ordersadd.cpp"},{"arguments":["clang","-Wno-documentation-unknown-command","-Wno-unknown-warning-option","-Wno-unknown-pragmas","-nostdinc","-nostdinc++","-std=gnu++1z","-Wall","-Wextra","-Wextra","-fexceptions","-mthreads","-fsyntax-only","-m64","--target=x86_64-w64-mingw32","-DUNICODE","-D_UNICODE","-DWIN32","-DMINGW_HAS_SECURE_API","-DQT_NO_DEBUG","-DQT_PRINTSUPPORT_LIB","-DQT_CHARTS_LIB","-DQT_OPENGLWIDGETS_LIB","-DQT_WIDGETS_LIB","-DQT_OPENGL_LIB","-DQT_GUI_LIB","-DQT_SQL_LIB","-DQT_CORE_LIB","-DQT_NEEDS_QMAIN","-DQ_CREATOR_RUN","-IC:\\Qt\\Tools\\QtCreator\\share\\qtcreator\\cplusplus\\wrappedMingwHeaders","-IC:\\Qt\\Tools\\QtCreator\\share\\qtcreator\\cplusplus\\wrappedQtHeaders","-IC:\\Qt\\Tools\\QtCreator\\share\\qtcreator\\cplusplus\\wrappedQtHeaders\\QtCore","-ID:\\qt\\qt\\STO2","-IC:\\Qt\\6.4.1\\mingw_64\\include","-IC:\\Qt\\6.4.1\\mingw_64\\include\\QtPrintSupport","-IC:\\Qt\\6.4.1\\mingw_64\\include\\QtCharts","-IC:\\Qt\\6.4.1\\mingw_64\\include\\QtOpenGLWidgets","-IC:\\Qt\\6.4.1\\mingw_64\\include\\QtWidgets","-IC:\\Qt\\6.4.1\\mingw_64\\include\\QtOpenGL","-IC:\\Qt\\6.4.1\\mingw_64\\include\\QtGui","-IC:\\Qt\\6.4.1\\mingw_64\\include\\QtSql","-IC:\\Qt\\6.4.1\\mingw_64\\include\\QtCore","-ID:\\qt\\qt\\STO2\\release","-IC:\\Qt\\6.4.1\\mingw_64\\mkspecs\\win32-g++","-isystem","C:\\Qt\\Tools\\mingw1120_64\\lib\\gcc\\x86_64-w64-mingw32\\11.2.0\\include\\c++","-isystem","C:\\Qt\\Tools\\mingw1120_64\\lib\\gcc\\x86_64-w64-mingw32\\11.2.0\\include\\c++\\x86_64-w64-mingw32","-isystem","C:\\Qt\\Tools\\mingw1120_64\\lib\\gcc\\x86_64-w64-mingw32\\11.2.0\\include\\c++\\backward","-isystem","C:\\Qt\\Tools\\QtCreator\\bin\\clang\\lib\\clang\\15.0.0\\include","-isystem","C:\\Qt\\Tools\\mingw1120_64\\x86_64-w64-mingw32\\include","-fmessage-length=0","-fdiagnostics-show-note-include-stack","-fretain-comments-from-system-headers","-fmacro-backtrace-limit=0","-ferror-limit=1000","-x","c++","D:\\qt\\qt\\STO2\\partsalesadd.cpp"],"directory":"D:/qt/qt/STO2/.qtc_clangd","file":"D:/qt/qt/STO2/partsalesadd.cpp"},{"arguments":["clang","-Wno-documentation-unknown-command","-Wno-unknown-warning-option","-Wno-unknown-pragmas","-nostdinc","-nostdinc++","-std=gnu++1z","-Wall","-Wextra","-Wextra","-fexceptions","-mthreads","-fsyntax-only","-m64","--target=x86_64-w64-mingw32","-DUNICODE","-D_UNICODE","-DWIN32","-DMINGW_HAS_SECURE_API","-DQT_NO_DEBUG","-DQT_PRINTSUPPORT_LIB","-DQT_CHARTS_LIB","-DQT_OPENGLWIDGETS_LIB","-DQT_WIDGETS_LIB","-DQT_OPENGL_LIB","-DQT_GUI_LIB","-DQT_SQL_LIB","-DQT_CORE_LIB","-DQT_NEEDS_QMAIN","-DQ_CREATOR_RUN","-IC:\\Qt\\Tools\\QtCreator\\share\\qtcreator\\cplusplus\\wrappedMingwHeaders","-IC:\\Qt\\Tools\\QtCreator\\share\\qtcreator\\cplusplus\\wrappedQtHeaders","-IC:\\Qt\\Tools\\QtCreator\\share\\qtcreator\\cplusplus\\wrappedQtHeaders\\QtCore","-ID:\\qt\\qt\\STO2","-IC:\\Qt\\6.4.1\\mingw_64\\include","-IC:\\Qt\\6.4.1\\mingw_64\\include\\QtPrintSupport","-IC:\\Qt\\6.4.1\\mingw_64\\include\\QtCharts","-IC:\\Qt\\6.4.1\\mingw_64\\include\\QtOpenGLWidgets","-IC:\\Qt\\6.4.1\\mingw_64\\include\\QtWidgets","-IC:\\Qt\\6.4.1\\mingw_64\\include\\QtOpenGL","-IC:\\Qt\\6.4.1\\mingw_64\\include\\QtGui","-IC:\\Qt\\6.4.1\\mingw_64\\include\\QtSql","-IC:\\Qt\\6.4.1\\mingw_64\\include\\QtCore","-ID:\\qt\\qt\\STO2\\release","-IC:\\Qt\\6.4.1\\mingw_64\\mkspecs\\win32-g++","-isystem","C:\\Qt\\Tools\\mingw1120_64\\lib\\gcc\\x86_64-w64-mingw32\\11.2.0\\include\\c++","-isystem","C:\\Qt\\Tools\\mingw1120_64\\lib\\gcc\\x86_64-w64-mingw32\\11.2.0\\include\\c++\\x86_64-w64-mingw32","-isystem","C:\\Qt\\Tools\\mingw1120_64\\lib\\gcc\\x86_64-w64-mingw32\\11.2.0\\include\\c++\\backward","-isystem","C:\\Qt\\Tools\\QtCreator\\bin\\clang\\lib\\clang\\15.0.0\\include","-isystem","C:\\Qt\\Tools\\mingw1120_64\\x86_64-w64-mingw32\\include","-fmessage-length=0","-fdiagnostics-show-note-include-stack","-fretain-comments-from-system-headers","-fmacro-backtrace-limit=0","-ferror-limit=1000","-x","c++","D:\\qt\\qt\\STO2\\rempogar.cpp"],"directory":"D:/qt/qt/STO2/.qtc_clangd","file":"D:/qt/qt/STO2/rempogar.cpp"},{"arguments":["clang","-Wno-documentation-unknown-command","-Wno-unknown-warning-option","-Wno-unknown-pragmas","-nostdinc","-nostdinc++","-std=gnu++1z","-Wall","-Wextra","-Wextra","-fexceptions","-mthreads","-fsyntax-only","-m64","--target=x86_64-w64-mingw32","-DUNICODE","-D_UNICODE","-DWIN32","-DMINGW_HAS_SECURE_API","-DQT_NO_DEBUG","-DQT_PRINTSUPPORT_LIB","-DQT_CHARTS_LIB","-DQT_OPENGLWIDGETS_LIB","-DQT_WIDGETS_LIB","-DQT_OPENGL_LIB","-DQT_GUI_LIB","-DQT_SQL_LIB","-DQT_CORE_LIB","-DQT_NEEDS_QMAIN","-DQ_CREATOR_RUN","-IC:\\Qt\\Tools\\QtCreator\\share\\qtcreator\\cplusplus\\wrappedMingwHeaders","-IC:\\Qt\\Tools\\QtCreator\\share\\qtcreator\\cplusplus\\wrappedQtHeaders","-IC:\\Qt\\Tools\\QtCreator\\share\\qtcreator\\cplusplus\\wrappedQtHeaders\\QtCore","-ID:\\qt\\qt\\STO2","-IC:\\Qt\\6.4.1\\mingw_64\\include","-IC:\\Qt\\6.4.1\\mingw_64\\include\\QtPrintSupport","-IC:\\Qt\\6.4.1\\mingw_64\\include\\QtCharts","-IC:\\Qt\\6.4.1\\mingw_64\\include\\QtOpenGLWidgets","-IC:\\Qt\\6.4.1\\mingw_64\\include\\QtWidgets","-IC:\\Qt\\6.4.1\\mingw_64\\include\\QtOpenGL","-IC:\\Qt\\6.4.1\\mingw_64\\include\\QtGui","-IC:\\Qt\\6.4.1\\mingw_64\\include\\QtSql","-IC:\\Qt\\6.4.1\\mingw_64\\include\\QtCore","-ID:\\qt\\qt\\STO2\\release","-IC:\\Qt\\6.4.1\\mingw_64\\mkspecs\\win32-g++","-isystem","C:\\Qt\\Tools\\mingw1120_64\\lib\\gcc\\x86_64-w64-mingw32\\11.2.0\\include\\c++","-isystem","C:\\Qt\\Tools\\mingw1120_64\\lib\\gcc\\x86_64-w64-mingw32\\11.2.0\\include\\c++\\x86_64-w64-mingw32","-isystem","C:\\Qt\\Tools\\mingw1120_64\\lib\\gcc\\x86_64-w64-mingw32\\11.2.0\\include\\c++\\backward","-isystem","C:\\Qt\\Tools\\QtCreator\\bin\\clang\\lib\\clang\\15.0.0\\include","-isystem","C:\\Qt\\Tools\\mingw1120_64\\x86_64-w64-mingw32\\include","-fmessage-length=0","-fdiagnostics-show-note-include-stack","-fretain-comments-from-system-headers","-fmacro-backtrace-limit=0","-ferror-limit=1000","-x","c++","D:\\qt\\qt\\STO2\\reviews.cpp"],"directory":"D:/qt/qt/STO2/.qtc_clangd","file":"D:/qt/qt/STO2/reviews.cpp"},{"arguments":["clang","-Wno-documentation-unknown-command","-Wno-unknown-warning-option","-Wno-unknown-pragmas","-nostdinc","-nostdinc++","-std=gnu++1z","-Wall","-Wextra","-Wextra","-fexceptions","-mthreads","-fsyntax-only","-m64","--target=x86_64-w64-mingw32","-DUNICODE","-D_UNICODE","-DWIN32","-DMINGW_HAS_SECURE_API","-DQT_NO_DEBUG","-DQT_PRINTSUPPORT_LIB","-DQT_CHARTS_LIB","-DQT_OPENGLWIDGETS_LIB","-DQT_WIDGETS_LIB","-DQT_OPENGL_LIB","-DQT_GUI_LIB","-DQT_SQL_LIB","-DQT_CORE_LIB","-DQT_NEEDS_QMAIN","-DQ_CREATOR_RUN","-IC:\\Qt\\Tools\\QtCreator\\share\\qtcreator\\cplusplus\\wrappedMingwHeaders","-IC:\\Qt\\Tools\\QtCreator\\share\\qtcreator\\cplusplus\\wrappedQtHeaders","-IC:\\Qt\\Tools\\QtCreator\\share\\qtcreator\\cplusplus\\wrappedQtHeaders\\QtCore","-ID:\\qt\\qt\\STO2","-IC:\\Qt\\6.4.1\\mingw_64\\include","-IC:\\Qt\\6.4.1\\mingw_64\\include\\QtPrintSupport","-IC:\\Qt\\6.4.1\\mingw_64\\include\\QtCharts","-IC:\\Qt\\6.4.1\\mingw_64\\include\\QtOpenGLWidgets","-IC:\\Qt\\6.4.1\\mingw_64\\include\\QtWidgets","-IC:\\Qt\\6.4.1\\mingw_64\\include\\QtOpenGL","-IC:\\Qt\\6.4.1\\mingw_64\\include\\QtGui","-IC:\\Qt\\6.4.1\\mingw_64\\include\\QtSql","-IC:\\Qt\\6.4.1\\mingw_64\\include\\QtCore","-ID:\\qt\\qt\\STO2\\release","-IC:\\Qt\\6.4.1\\mingw_64\\mkspecs\\win32-g++","-isystem","C:\\Qt\\Tools\\mingw1120_64\\lib\\gcc\\x86_64-w64-mingw32\\11.2.0\\include\\c++","-isystem","C:\\Qt\\Tools\\mingw1120_64\\lib\\gcc\\x86_64-w64-mingw32\\11.2.0\\include\\c++\\x86_64-w64-mingw32","-isystem","C:\\Qt\\Tools\\mingw1120_64\\lib\\gcc\\x86_64-w64-mingw32\\11.2.0\\include\\c++\\backward","-isystem","C:\\Qt\\Tools\\QtCreator\\bin\\clang\\lib\\clang\\15.0.0\\include","-isystem","C:\\Qt\\Tools\\mingw1120_64\\x86_64-w64-mingw32\\include","-fmessage-length=0","-fdiagnostics-show-note-include-stack","-fretain-comments-from-system-headers","-fmacro-backtrace-limit=0","-ferror-limit=1000","-x","c++","D:\\qt\\qt\\STO2\\servicesadd.cpp"],"directory":"D:/qt/qt/STO2/.qtc_clangd","file":"D:/qt/qt/STO2/servicesadd.cpp"},{"arguments":["clang","-Wno-documentation-unknown-command","-Wno-unknown-warning-option","-Wno-unknown-pragmas","-nostdinc","-nostdinc++","-std=gnu++1z","-Wall","-Wextra","-Wextra","-fexceptions","-mthreads","-fsyntax-only","-m64","--target=x86_64-w64-mingw32","-DUNICODE","-D_UNICODE","-DWIN32","-DMINGW_HAS_SECURE_API","-DQT_NO_DEBUG","-DQT_PRINTSUPPORT_LIB","-DQT_CHARTS_LIB","-DQT_OPENGLWIDGETS_LIB","-DQT_WIDGETS_LIB","-DQT_OPENGL_LIB","-DQT_GUI_LIB","-DQT_SQL_LIB","-DQT_CORE_LIB","-DQT_NEEDS_QMAIN","-DQ_CREATOR_RUN","-IC:\\Qt\\Tools\\QtCreator\\share\\qtcreator\\cplusplus\\wrappedMingwHeaders","-IC:\\Qt\\Tools\\QtCreator\\share\\qtcreator\\cplusplus\\wrappedQtHeaders","-IC:\\Qt\\Tools\\QtCreator\\share\\qtcreator\\cplusplus\\wrappedQtHeaders\\QtCore","-ID:\\qt\\qt\\STO2","-IC:\\Qt\\6.4.1\\mingw_64\\include","-IC:\\Qt\\6.4.1\\mingw_64\\include\\QtPrintSupport","-IC:\\Qt\\6.4.1\\mingw_64\\include\\QtCharts","-IC:\\Qt\\6.4.1\\mingw_64\\include\\QtOpenGLWidgets","-IC:\\Qt\\6.4.1\\mingw_64\\include\\QtWidgets","-IC:\\Qt\\6.4.1\\mingw_64\\include\\QtOpenGL","-IC:\\Qt\\6.4.1\\mingw_64\\include\\QtGui","-IC:\\Qt\\6.4.1\\mingw_64\\include\\QtSql","-IC:\\Qt\\6.4.1\\mingw_64\\include\\QtCore","-ID:\\qt\\qt\\STO2\\release","-IC:\\Qt\\6.4.1\\mingw_64\\mkspecs\\win32-g++","-isystem","C:\\Qt\\Tools\\mingw1120_64\\lib\\gcc\\x86_64-w64-mingw32\\11.2.0\\include\\c++","-isystem","C:\\Qt\\Tools\\mingw1120_64\\lib\\gcc\\x86_64-w64-mingw32\\11.2.0\\include\\c++\\x86_64-w64-mingw32","-isystem","C:\\Qt\\Tools\\mingw1120_64\\lib\\gcc\\x86_64-w64-mingw32\\11.2.0\\include\\c++\\backward","-isystem","C:\\Qt\\Tools\\QtCreator\\bin\\clang\\lib\\clang\\15.0.0\\include","-isystem","C:\\Qt\\Tools\\mingw1120_64\\x86_64-w64-mingw32\\include","-fmessage-length=0","-fdiagnostics-show-note-include-stack","-fretain-comments-from-system-headers","-fmacro-backtrace-limit=0","-ferror-limit=1000","-x","c++","D:\\qt\\qt\\STO2\\sparapartsadd.cpp"],"directory":"D:/qt/qt/STO2/.qtc_clangd","file":"D:/qt/qt/STO2/sparapartsadd.cpp"},{"arguments":["clang","-Wno-documentation-unknown-command","-Wno-unknown-warning-option","-Wno-unknown-pragmas","-nostdinc","-nostdinc++","-std=gnu++1z","-Wall","-Wextra","-Wextra","-fexceptions","-mthreads","-fsyntax-only","-m64","--target=x86_64-w64-mingw32","-DUNICODE","-D_UNICODE","-DWIN32","-DMINGW_HAS_SECURE_API","-DQT_NO_DEBUG","-DQT_PRINTSUPPORT_LIB","-DQT_CHARTS_LIB","-DQT_OPENGLWIDGETS_LIB","-DQT_WIDGETS_LIB","-DQT_OPENGL_LIB","-DQT_GUI_LIB","-DQT_SQL_LIB","-DQT_CORE_LIB","-DQT_NEEDS_QMAIN","-DQ_CREATOR_RUN","-IC:\\Qt\\Tools\\QtCreator\\share\\qtcreator\\cplusplus\\wrappedMingwHeaders","-IC:\\Qt\\Tools\\QtCreator\\share\\qtcreator\\cplusplus\\wrappedQtHeaders","-IC:\\Qt\\Tools\\QtCreator\\share\\qtcreator\\cplusplus\\wrappedQtHeaders\\QtCore","-ID:\\qt\\qt\\STO2","-IC:\\Qt\\6.4.1\\mingw_64\\include","-IC:\\Qt\\6.4.1\\mingw_64\\include\\QtPrintSupport","-IC:\\Qt\\6.4.1\\mingw_64\\include\\QtCharts","-IC:\\Qt\\6.4.1\\mingw_64\\include\\QtOpenGLWidgets","-IC:\\Qt\\6.4.1\\mingw_64\\include\\QtWidgets","-IC:\\Qt\\6.4.1\\mingw_64\\include\\QtOpenGL","-IC:\\Qt\\6.4.1\\mingw_64\\include\\QtGui","-IC:\\Qt\\6.4.1\\mingw_64\\include\\QtSql","-IC:\\Qt\\6.4.1\\mingw_64\\include\\QtCore","-ID:\\qt\\qt\\STO2\\release","-IC:\\Qt\\6.4.1\\mingw_64\\mkspecs\\win32-g++","-isystem","C:\\Qt\\Tools\\mingw1120_64\\lib\\gcc\\x86_64-w64-mingw32\\11.2.0\\include\\c++","-isystem","C:\\Qt\\Tools\\mingw1120_64\\lib\\gcc\\x86_64-w64-mingw32\\11.2.0\\include\\c++\\x86_64-w64-mingw32","-isystem","C:\\Qt\\Tools\\mingw1120_64\\lib\\gcc\\x86_64-w64-mingw32\\11.2.0\\include\\c++\\backward","-isystem","C:\\Qt\\Tools\\QtCreator\\bin\\clang\\lib\\clang\\15.0.0\\include","-isystem","C:\\Qt\\Tools\\mingw1120_64\\x86_64-w64-mingw32\\include","-fmessage-length=0","-fdiagnostics-show-note-include-stack","-fretain-comments-from-system-headers","-fmacro-backtrace-limit=0","-ferror-limit=1000","-x","c++","D:\\qt\\qt\\STO2\\staffadd.cpp"],"directory":"D:/qt/qt/STO2/.qtc_clangd","file":"D:/qt/qt/STO2/staffadd.cpp"},{"arguments":["clang","-Wno-documentation-unknown-command","-Wno-unknown-warning-option","-Wno-unknown-pragmas","-nostdinc","-nostdinc++","-std=gnu++1z","-Wall","-Wextra","-Wextra","-fexceptions","-mthreads","-fsyntax-only","-m64","--target=x86_64-w64-mingw32","-DUNICODE","-D_UNICODE","-DWIN32","-DMINGW_HAS_SECURE_API","-DQT_NO_DEBUG","-DQT_PRINTSUPPORT_LIB","-DQT_CHARTS_LIB","-DQT_OPENGLWIDGETS_LIB","-DQT_WIDGETS_LIB","-DQT_OPENGL_LIB","-DQT_GUI_LIB","-DQT_SQL_LIB","-DQT_CORE_LIB","-DQT_NEEDS_QMAIN","-DQ_CREATOR_RUN","-IC:\\Qt\\Tools\\QtCreator\\share\\qtcreator\\cplusplus\\wrappedMingwHeaders","-IC:\\Qt\\Tools\\QtCreator\\share\\qtcreator\\cplusplus\\wrappedQtHeaders","-IC:\\Qt\\Tools\\QtCreator\\share\\qtcreator\\cplusplus\\wrappedQtHeaders\\QtCore","-ID:\\qt\\qt\\STO2","-IC:\\Qt\\6.4.1\\mingw_64\\include","-IC:\\Qt\\6.4.1\\mingw_64\\include\\QtPrintSupport","-IC:\\Qt\\6.4.1\\mingw_64\\include\\QtCharts","-IC:\\Qt\\6.4.1\\mingw_64\\include\\QtOpenGLWidgets","-IC:\\Qt\\6.4.1\\mingw_64\\include\\QtWidgets","-IC:\\Qt\\6.4.1\\mingw_64\\include\\QtOpenGL","-IC:\\Qt\\6.4.1\\mingw_64\\include\\QtGui","-IC:\\Qt\\6.4.1\\mingw_64\\include\\QtSql","-IC:\\Qt\\6.4.1\\mingw_64\\include\\QtCore","-ID:\\qt\\qt\\STO2\\release","-IC:\\Qt\\6.4.1\\mingw_64\\mkspecs\\win32-g++","-isystem","C:\\Qt\\Tools\\mingw1120_64\\lib\\gcc\\x86_64-w64-mingw32\\11.2.0\\include\\c++","-isystem","C:\\Qt\\Tools\\mingw1120_64\\lib\\gcc\\x86_64-w64-mingw32\\11.2.0\\include\\c++\\x86_64-w64-mingw32","-isystem","C:\\Qt\\Tools\\mingw1120_64\\lib\\gcc\\x86_64-w64-mingw32\\11.2.0\\include\\c++\\backward","-isystem","C:\\Qt\\Tools\\QtCreator\\bin\\clang\\lib\\clang\\15.0.0\\include","-isystem","C:\\Qt\\Tools\\mingw1120_64\\x86_64-w64-mingw32\\include","-fmessage-length=0","-fdiagnostics-show-note-include-stack","-fretain-comments-from-system-headers","-fmacro-backtrace-limit=0","-ferror-limit=1000","-x","c++","D:\\qt\\qt\\STO2\\viewtablesto.cpp"],"directory":"D:/qt/qt/STO2/.qtc_clangd","file":"D:/qt/qt/STO2/viewtablesto.cpp"},{"arguments":["clang","-Wno-documentation-unknown-command","-Wno-unknown-warning-option","-Wno-unknown-pragmas","-nostdinc","-nostdinc++","-std=gnu++1z","-Wall","-Wextra","-Wextra","-fexceptions","-mthreads","-fsyntax-only","-m64","--target=x86_64-w64-mingw32","-DUNICODE","-D_UNICODE","-DWIN32","-DMINGW_HAS_SECURE_API","-DQT_NO_DEBUG","-DQT_PRINTSUPPORT_LIB","-DQT_CHARTS_LIB","-DQT_OPENGLWIDGETS_LIB","-DQT_WIDGETS_LIB","-DQT_OPENGL_LIB","-DQT_GUI_LIB","-DQT_SQL_LIB","-DQT_CORE_LIB","-DQT_NEEDS_QMAIN","-DQ_CREATOR_RUN","-IC:\\Qt\\Tools\\QtCreator\\share\\qtcreator\\cplusplus\\wrappedMingwHeaders","-IC:\\Qt\\Tools\\QtCreator\\share\\qtcreator\\cplusplus\\wrappedQtHeaders","-IC:\\Qt\\Tools\\QtCreator\\share\\qtcreator\\cplusplus\\wrappedQtHeaders\\QtCore","-ID:\\qt\\qt\\STO2","-IC:\\Qt\\6.4.1\\mingw_64\\include","-IC:\\Qt\\6.4.1\\mingw_64\\include\\QtPrintSupport","-IC:\\Qt\\6.4.1\\mingw_64\\include\\QtCharts","-IC:\\Qt\\6.4.1\\mingw_64\\include\\QtOpenGLWidgets","-IC:\\Qt\\6.4.1\\mingw_64\\include\\QtWidgets","-IC:\\Qt\\6.4.1\\mingw_64\\include\\QtOpenGL","-IC:\\Qt\\6.4.1\\mingw_64\\include\\QtGui","-IC:\\Qt\\6.4.1\\mingw_64\\include\\QtSql","-IC:\\Qt\\6.4.1\\mingw_64\\include\\QtCore","-ID:\\qt\\qt\\STO2\\release","-IC:\\Qt\\6.4.1\\mingw_64\\mkspecs\\win32-g++","-isystem","C:\\Qt\\Tools\\mingw1120_64\\lib\\gcc\\x86_64-w64-mingw32\\11.2.0\\include\\c++","-isystem","C:\\Qt\\Tools\\mingw1120_64\\lib\\gcc\\x86_64-w64-mingw32\\11.2.0\\include\\c++\\x86_64-w64-mingw32","-isystem","C:\\Qt\\Tools\\mingw1120_64\\lib\\gcc\\x86_64-w64-mingw32\\11.2.0\\include\\c++\\backward","-isystem","C:\\Qt\\Tools\\QtCreator\\bin\\clang\\lib\\clang\\15.0.0\\include","-isystem","C:\\Qt\\Tools\\mingw1120_64\\x86_64-w64-mingw32\\include","-fmessage-length=0","-fdiagnostics-show-note-include-stack","-fretain-comments-from-system-headers","-fmacro-backtrace-limit=0","-ferror-limit=1000","-x","c++","D:\\qt\\qt\\STO2\\warrantycasesadd.cpp"],"directory":"D:/qt/qt/STO2/.qtc_clangd","file":"D:/qt/qt/STO2/warrantycasesadd.cpp"},{"arguments":["clang","-Wno-documentation-unknown-command","-Wno-unknown-warning-option","-Wno-unknown-pragmas","-nostdinc","-nostdinc++","-std=gnu++1z","-Wall","-Wextra","-Wextra","-fexceptions","-mthreads","-fsyntax-only","-m64","--target=x86_64-w64-mingw32","-DUNICODE","-D_UNICODE","-DWIN32","-DMINGW_HAS_SECURE_API","-DQT_NO_DEBUG","-DQT_PRINTSUPPORT_LIB","-DQT_CHARTS_LIB","-DQT_OPENGLWIDGETS_LIB","-DQT_WIDGETS_LIB","-DQT_OPENGL_LIB","-DQT_GUI_LIB","-DQT_SQL_LIB","-DQT_CORE_LIB","-DQT_NEEDS_QMAIN","-DQ_CREATOR_RUN","-IC:\\Qt\\Tools\\QtCreator\\share\\qtcreator\\cplusplus\\wrappedMingwHeaders","-IC:\\Qt\\Tools\\QtCreator\\share\\qtcreator\\cplusplus\\wrappedQtHeaders","-IC:\\Qt\\Tools\\QtCreator\\share\\qtcreator\\cplusplus\\wrappedQtHeaders\\QtCore","-ID:\\qt\\qt\\STO2","-IC:\\Qt\\6.4.1\\mingw_64\\include","-IC:\\Qt\\6.4.1\\mingw_64\\include\\QtPrintSupport","-IC:\\Qt\\6.4.1\\mingw_64\\include\\QtCharts","-IC:\\Qt\\6.4.1\\mingw_64\\include\\QtOpenGLWidgets","-IC:\\Qt\\6.4.1\\mingw_64\\include\\QtWidgets","-IC:\\Qt\\6.4.1\\mingw_64\\include\\QtOpenGL","-IC:\\Qt\\6.4.1\\mingw_64\\include\\QtGui","-IC:\\Qt\\6.4.1\\mingw_64\\include\\QtSql","-IC:\\Qt\\6.4.1\\mingw_64\\include\\QtCore","-ID:\\qt\\qt\\STO2\\release","-IC:\\Qt\\6.4.1\\mingw_64\\mkspecs\\win32-g++","-isystem","C:\\Qt\\Tools\\mingw1120_64\\lib\\gcc\\x86_64-w64-mingw32\\11.2.0\\include\\c++","-isystem","C:\\Qt\\Tools\\mingw1120_64\\lib\\gcc\\x86_64-w64-mingw32\\11.2.0\\include\\c++\\x86_64-w64-mingw32","-isystem","C:\\Qt\\Tools\\mingw1120_64\\lib\\gcc\\x86_64-w64-mingw32\\11.2.0\\include\\c++\\backward","-isystem","C:\\Qt\\Tools\\QtCreator\\bin\\clang\\lib\\clang\\15.0.0\\include","-isystem","C:\\Qt\\Tools\\mingw1120_64\\x86_64-w64-mingw32\\include","-fmessage-length=0","-fdiagnostics-show-note-include-stack","-fretain-comments-from-system-headers","-fmacro-backtrace-limit=0","-ferror-limit=1000","-x","c++","D:\\qt\\qt\\STO2\\warrantyrepairsadd.cpp"],"directory":"D:/qt/qt/STO2/.qtc_clangd","file":"D:/qt/qt/STO2/warrantyrepairsadd.cpp"},{"arguments":["clang","-Wno-documentation-unknown-command","-Wno-unknown-warning-option","-Wno-unknown-pragmas","-nostdinc","-nostdinc++","-std=gnu++1z","-Wall","-Wextra","-Wextra","-fexceptions","-mthreads","-fsyntax-only","-m64","--target=x86_64-w64-mingw32","-DUNICODE","-D_UNICODE","-DWIN32","-DMINGW_HAS_SECURE_API","-DQT_NO_DEBUG","-DQT_PRINTSUPPORT_LIB","-DQT_CHARTS_LIB","-DQT_OPENGLWIDGETS_LIB","-DQT_WIDGETS_LIB","-DQT_OPENGL_LIB","-DQT_GUI_LIB","-DQT_SQL_LIB","-DQT_CORE_LIB","-DQT_NEEDS_QMAIN","-DQ_CREATOR_RUN","-IC:\\Qt\\Tools\\QtCreator\\share\\qtcreator\\cplusplus\\wrappedMingwHeaders","-IC:\\Qt\\Tools\\QtCreator\\share\\qtcreator\\cplusplus\\wrappedQtHeaders","-IC:\\Qt\\Tools\\QtCreator\\share\\qtcreator\\cplusplus\\wrappedQtHeaders\\QtCore","-ID:\\qt\\qt\\STO2","-IC:\\Qt\\6.4.1\\mingw_64\\include","-IC:\\Qt\\6.4.1\\mingw_64\\include\\QtPrintSupport","-IC:\\Qt\\6.4.1\\mingw_64\\include\\QtCharts","-IC:\\Qt\\6.4.1\\mingw_64\\include\\QtOpenGLWidgets","-IC:\\Qt\\6.4.1\\mingw_64\\include\\QtWidgets","-IC:\\Qt\\6.4.1\\mingw_64\\include\\QtOpenGL","-IC:\\Qt\\6.4.1\\mingw_64\\include\\QtGui","-IC:\\Qt\\6.4.1\\mingw_64\\include\\QtSql","-IC:\\Qt\\6.4.1\\mingw_64\\include\\QtCore","-ID:\\qt\\qt\\STO2\\release","-IC:\\Qt\\6.4.1\\mingw_64\\mkspecs\\win32-g++","-isystem","C:\\Qt\\Tools\\mingw1120_64\\lib\\gcc\\x86_64-w64-mingw32\\11.2.0\\include\\c++","-isystem","C:\\Qt\\Tools\\mingw1120_64\\lib\\gcc\\x86_64-w64-mingw32\\11.2.0\\include\\c++\\x86_64-w64-mingw32","-isystem","C:\\Qt\\Tools\\mingw1120_64\\lib\\gcc\\x86_64-w64-mingw32\\11.2.0\\include\\c++\\backward","-isystem","C:\\Qt\\Tools\\QtCreator\\bin\\clang\\lib\\clang\\15.0.0\\include","-isystem","C:\\Qt\\Tools\\mingw1120_64\\x86_64-w64-mingw32\\include","-fmessage-length=0","-fdiagnostics-show-note-include-stack","-fretain-comments-from-system-headers","-fmacro-backtrace-limit=0","-ferror-limit=1000","-x","c++","D:\\qt\\qt\\STO2\\warsot.cpp"],"directory":"D:/qt/qt/STO2/.qtc_clangd","file":"D:/qt/qt/STO2/warsot.cpp"},{"arguments":["clang","-Wno-documentation-unknown-command","-Wno-unknown-warning-option","-Wno-unknown-pragmas","-nostdinc","-nostdinc++","-std=gnu++1z","-Wall","-Wextra","-Wextra","-fexceptions","-mthreads","-fsyntax-only","-m64","--target=x86_64-w64-mingw32","-DUNICODE","-D_UNICODE","-DWIN32","-DMINGW_HAS_SECURE_API","-DQT_NO_DEBUG","-DQT_PRINTSUPPORT_LIB","-DQT_CHARTS_LIB","-DQT_OPENGLWIDGETS_LIB","-DQT_WIDGETS_LIB","-DQT_OPENGL_LIB","-DQT_GUI_LIB","-DQT_SQL_LIB","-DQT_CORE_LIB","-DQT_NEEDS_QMAIN","-DQ_CREATOR_RUN","-IC:\\Qt\\Tools\\QtCreator\\share\\qtcreator\\cplusplus\\wrappedMingwHeaders","-IC:\\Qt\\Tools\\QtCreator\\share\\qtcreator\\cplusplus\\wrappedQtHeaders","-IC:\\Qt\\Tools\\QtCreator\\share\\qtcreator\\cplusplus\\wrappedQtHeaders\\QtCore","-ID:\\qt\\qt\\STO2","-IC:\\Qt\\6.4.1\\mingw_64\\include","-IC:\\Qt\\6.4.1\\mingw_64\\include\\QtPrintSupport","-IC:\\Qt\\6.4.1\\mingw_64\\include\\QtCharts","-IC:\\Qt\\6.4.1\\mingw_64\\include\\QtOpenGLWidgets","-IC:\\Qt\\6.4.1\\mingw_64\\include\\QtWidgets","-IC:\\Qt\\6.4.1\\mingw_64\\include\\QtOpenGL","-IC:\\Qt\\6.4.1\\mingw_64\\include\\QtGui","-IC:\\Qt\\6.4.1\\mingw_64\\include\\QtSql","-IC:\\Qt\\6.4.1\\mingw_64\\include\\QtCore","-ID:\\qt\\qt\\STO2\\release","-IC:\\Qt\\6.4.1\\mingw_64\\mkspecs\\win32-g++","-isystem","C:\\Qt\\Tools\\mingw1120_64\\lib\\gcc\\x86_64-w64-mingw32\\11.2.0\\include\\c++","-isystem","C:\\Qt\\Tools\\mingw1120_64\\lib\\gcc\\x86_64-w64-mingw32\\11.2.0\\include\\c++\\x86_64-w64-mingw32","-isystem","C:\\Qt\\Tools\\mingw1120_64\\lib\\gcc\\x86_64-w64-mingw32\\11.2.0\\include\\c++\\backward","-isystem","C:\\Qt\\Tools\\QtCreator\\bin\\clang\\lib\\clang\\15.0.0\\include","-isystem","C:\\Qt\\Tools\\mingw1120_64\\x86_64-w64-mingw32\\include","-fmessage-length=0","-fdiagnostics-show-note-include-stack","-fretain-comments-from-system-headers","-fmacro-backtrace-limit=0","-ferror-limit=1000","-x","c++","D:\\qt\\qt\\STO2\\workshuduleadd.cpp"],"directory":"D:/qt/qt/STO2/.qtc_clangd","file":"D:/qt/qt/STO2/workshuduleadd.cpp"},{"arguments":["clang","-Wno-documentation-unknown-command","-Wno-unknown-warning-option","-Wno-unknown-pragmas","-nostdinc","-nostdinc++","-std=gnu++1z","-Wall","-Wextra","-Wextra","-fexceptions","-mthreads","-fsyntax-only","-m64","--target=x86_64-w64-mingw32","-DUNICODE","-D_UNICODE","-DWIN32","-DMINGW_HAS_SECURE_API","-DQT_NO_DEBUG","-DQT_PRINTSUPPORT_LIB","-DQT_CHARTS_LIB","-DQT_OPENGLWIDGETS_LIB","-DQT_WIDGETS_LIB","-DQT_OPENGL_LIB","-DQT_GUI_LIB","-DQT_SQL_LIB","-DQT_CORE_LIB","-DQT_NEEDS_QMAIN","-DQ_CREATOR_RUN","-IC:\\Qt\\Tools\\QtCreator\\share\\qtcreator\\cplusplus\\wrappedMingwHeaders","-IC:\\Qt\\Tools\\QtCreator\\share\\qtcreator\\cplusplus\\wrappedQtHeaders","-IC:\\Qt\\Tools\\QtCreator\\share\\qtcreator\\cplusplus\\wrappedQtHeaders\\QtCore","-ID:\\qt\\qt\\STO2","-IC:\\Qt\\6.4.1\\mingw_64\\include","-IC:\\Qt\\6.4.1\\mingw_64\\include\\QtPrintSupport","-IC:\\Qt\\6.4.1\\mingw_64\\include\\QtCharts","-IC:\\Qt\\6.4.1\\mingw_64\\include\\QtOpenGLWidgets","-IC:\\Qt\\6.4.1\\mingw_64\\include\\QtWidgets","-IC:\\Qt\\6.4.1\\mingw_64\\include\\QtOpenGL","-IC:\\Qt\\6.4.1\\mingw_64\\include\\QtGui","-IC:\\Qt\\6.4.1\\mingw_64\\include\\QtSql","-IC:\\Qt\\6.4.1\\mingw_64\\include\\QtCore","-ID:\\qt\\qt\\STO2\\release","-IC:\\Qt\\6.4.1\\mingw_64\\mkspecs\\win32-g++","-isystem","C:\\Qt\\Tools\\mingw1120_64\\lib\\gcc\\x86_64-w64-mingw32\\11.2.0\\include\\c++","-isystem","C:\\Qt\\Tools\\mingw1120_64\\lib\\gcc\\x86_64-w64-mingw32\\11.2.0\\include\\c++\\x86_64-w64-mingw32","-isystem","C:\\Qt\\Tools\\mingw1120_64\\lib\\gcc\\x86_64-w64-mingw32\\11.2.0\\include\\c++\\backward","-isystem","C:\\Qt\\Tools\\QtCreator\\bin\\clang\\lib\\clang\\15.0.0\\include","-isystem","C:\\Qt\\Tools\\mingw1120_64\\x86_64-w64-mingw32\\include","-fmessage-length=0","-fdiagnostics-show-note-include-stack","-fretain-comments-from-system-headers","-fmacro-backtrace-limit=0","-ferror-limit=1000","-x","c++-header","D:\\qt\\qt\\STO2\\clientadd.h"],"directory":"D:/qt/qt/STO2/.qtc_clangd","file":"D:/qt/qt/STO2/clientadd.h"},{"arguments":["clang","-Wno-documentation-unknown-command","-Wno-unknown-warning-option","-Wno-unknown-pragmas","-nostdinc","-nostdinc++","-std=gnu++1z","-Wall","-Wextra","-Wextra","-fexceptions","-mthreads","-fsyntax-only","-m64","--target=x86_64-w64-mingw32","-DUNICODE","-D_UNICODE","-DWIN32","-DMINGW_HAS_SECURE_API","-DQT_NO_DEBUG","-DQT_PRINTSUPPORT_LIB","-DQT_CHARTS_LIB","-DQT_OPENGLWIDGETS_LIB","-DQT_WIDGETS_LIB","-DQT_OPENGL_LIB","-DQT_GUI_LIB","-DQT_SQL_LIB","-DQT_CORE_LIB","-DQT_NEEDS_QMAIN","-DQ_CREATOR_RUN","-IC:\\Qt\\Tools\\QtCreator\\share\\qtcreator\\cplusplus\\wrappedMingwHeaders","-IC:\\Qt\\Tools\\QtCreator\\share\\qtcreator\\cplusplus\\wrappedQtHeaders","-IC:\\Qt\\Tools\\QtCreator\\share\\qtcreator\\cplusplus\\wrappedQtHeaders\\QtCore","-ID:\\qt\\qt\\STO2","-IC:\\Qt\\6.4.1\\mingw_64\\include","-IC:\\Qt\\6.4.1\\mingw_64\\include\\QtPrintSupport","-IC:\\Qt\\6.4.1\\mingw_64\\include\\QtCharts","-IC:\\Qt\\6.4.1\\mingw_64\\include\\QtOpenGLWidgets","-IC:\\Qt\\6.4.1\\mingw_64\\include\\QtWidgets","-IC:\\Qt\\6.4.1\\mingw_64\\include\\QtOpenGL","-IC:\\Qt\\6.4.1\\mingw_64\\include\\QtGui","-IC:\\Qt\\6.4.1\\mingw_64\\include\\QtSql","-IC:\\Qt\\6.4.1\\mingw_64\\include\\QtCore","-ID:\\qt\\qt\\STO2\\release","-IC:\\Qt\\6.4.1\\mingw_64\\mkspecs\\win32-g++","-isystem","C:\\Qt\\Tools\\mingw1120_64\\lib\\gcc\\x86_64-w64-mingw32\\11.2.0\\include\\c++","-isystem","C:\\Qt\\Tools\\mingw1120_64\\lib\\gcc\\x86_64-w64-mingw32\\11.2.0\\include\\c++\\x86_64-w64-mingw32","-isystem","C:\\Qt\\Tools\\mingw1120_64\\lib\\gcc\\x86_64-w64-mingw32\\11.2.0\\include\\c++\\backward","-isystem","C:\\Qt\\Tools\\QtCreator\\bin\\clang\\lib\\clang\\15.0.0\\include","-isystem","C:\\Qt\\Tools\\mingw1120_64\\x86_64-w64-mingw32\\include","-fmessage-length=0","-fdiagnostics-show-note-include-stack","-fretain-comments-from-system-headers","-fmacro-backtrace-limit=0","-ferror-limit=1000","-x","c++-header","D:\\qt\\qt\\STO2\\infobase.h"],"directory":"D:/qt/qt/STO2/.qtc_clangd","file":"D:/qt/qt/STO2/infobase.h"},{"arguments":["clang","-Wno-documentation-unknown-command","-Wno-unknown-warning-option","-Wno-unknown-pragmas","-nostdinc","-nostdinc++","-std=gnu++1z","-Wall","-Wextra","-Wextra","-fexceptions","-mthreads","-fsyntax-only","-m64","--target=x86_64-w64-mingw32","-DUNICODE","-D_UNICODE","-DWIN32","-DMINGW_HAS_SECURE_API","-DQT_NO_DEBUG","-DQT_PRINTSUPPORT_LIB","-DQT_CHARTS_LIB","-DQT_OPENGLWIDGETS_LIB","-DQT_WIDGETS_LIB","-DQT_OPENGL_LIB","-DQT_GUI_LIB","-DQT_SQL_LIB","-DQT_CORE_LIB","-DQT_NEEDS_QMAIN","-DQ_CREATOR_RUN","-IC:\\Qt\\Tools\\QtCreator\\share\\qtcreator\\cplusplus\\wrappedMingwHeaders","-IC:\\Qt\\Tools\\QtCreator\\share\\qtcreator\\cplusplus\\wrappedQtHeaders","-IC:\\Qt\\Tools\\QtCreator\\share\\qtcreator\\cplusplus\\wrappedQtHeaders\\QtCore","-ID:\\qt\\qt\\STO2","-IC:\\Qt\\6.4.1\\mingw_64\\include","-IC:\\Qt\\6.4.1\\mingw_64\\include\\QtPrintSupport","-IC:\\Qt\\6.4.1\\mingw_64\\include\\QtCharts","-IC:\\Qt\\6.4.1\\mingw_64\\include\\QtOpenGLWidgets","-IC:\\Qt\\6.4.1\\mingw_64\\include\\QtWidgets","-IC:\\Qt\\6.4.1\\mingw_64\\include\\QtOpenGL","-IC:\\Qt\\6.4.1\\mingw_64\\include\\QtGui","-IC:\\Qt\\6.4.1\\mingw_64\\include\\QtSql","-IC:\\Qt\\6.4.1\\mingw_64\\include\\QtCore","-ID:\\qt\\qt\\STO2\\release","-IC:\\Qt\\6.4.1\\mingw_64\\mkspecs\\win32-g++","-isystem","C:\\Qt\\Tools\\mingw1120_64\\lib\\gcc\\x86_64-w64-mingw32\\11.2.0\\include\\c++","-isystem","C:\\Qt\\Tools\\mingw1120_64\\lib\\gcc\\x86_64-w64-mingw32\\11.2.0\\include\\c++\\x86_64-w64-mingw32","-isystem","C:\\Qt\\Tools\\mingw1120_64\\lib\\gcc\\x86_64-w64-mingw32\\11.2.0\\include\\c++\\backward","-isystem","C:\\Qt\\Tools\\QtCreator\\bin\\clang\\lib\\clang\\15.0.0\\include","-isystem","C:\\Qt\\Tools\\mingw1120_64\\x86_64-w64-mingw32\\include","-fmessage-length=0","-fdiagnostics-show-note-include-stack","-fretain-comments-from-system-headers","-fmacro-backtrace-limit=0","-ferror-limit=1000","-x","c++-header","D:\\qt\\qt\\STO2\\mainwindow.h"],"directory":"D:/qt/qt/STO2/.qtc_clangd","file":"D:/qt/qt/STO2/mainwindow.h"},{"arguments":["clang","-Wno-documentation-unknown-command","-Wno-unknown-warning-option","-Wno-unknown-pragmas","-nostdinc","-nostdinc++","-std=gnu++1z","-Wall","-Wextra","-Wextra","-fexceptions","-mthreads","-fsyntax-only","-m64","--target=x86_64-w64-mingw32","-DUNICODE","-D_UNICODE","-DWIN32","-DMINGW_HAS_SECURE_API","-DQT_NO_DEBUG","-DQT_PRINTSUPPORT_LIB","-DQT_CHARTS_LIB","-DQT_OPENGLWIDGETS_LIB","-DQT_WIDGETS_LIB","-DQT_OPENGL_LIB","-DQT_GUI_LIB","-DQT_SQL_LIB","-DQT_CORE_LIB","-DQT_NEEDS_QMAIN","-DQ_CREATOR_RUN","-IC:\\Qt\\Tools\\QtCreator\\share\\qtcreator\\cplusplus\\wrappedMingwHeaders","-IC:\\Qt\\Tools\\QtCreator\\share\\qtcreator\\cplusplus\\wrappedQtHeaders","-IC:\\Qt\\Tools\\QtCreator\\share\\qtcreator\\cplusplus\\wrappedQtHeaders\\QtCore","-ID:\\qt\\qt\\STO2","-IC:\\Qt\\6.4.1\\mingw_64\\include","-IC:\\Qt\\6.4.1\\mingw_64\\include\\QtPrintSupport","-IC:\\Qt\\6.4.1\\mingw_64\\include\\QtCharts","-IC:\\Qt\\6.4.1\\mingw_64\\include\\QtOpenGLWidgets","-IC:\\Qt\\6.4.1\\mingw_64\\include\\QtWidgets","-IC:\\Qt\\6.4.1\\mingw_64\\include\\QtOpenGL","-IC:\\Qt\\6.4.1\\mingw_64\\include\\QtGui","-IC:\\Qt\\6.4.1\\mingw_64\\include\\QtSql","-IC:\\Qt\\6.4.1\\mingw_64\\include\\QtCore","-ID:\\qt\\qt\\STO2\\release","-IC:\\Qt\\6.4.1\\mingw_64\\mkspecs\\win32-g++","-isystem","C:\\Qt\\Tools\\mingw1120_64\\lib\\gcc\\x86_64-w64-mingw32\\11.2.0\\include\\c++","-isystem","C:\\Qt\\Tools\\mingw1120_64\\lib\\gcc\\x86_64-w64-mingw32\\11.2.0\\include\\c++\\x86_64-w64-mingw32","-isystem","C:\\Qt\\Tools\\mingw1120_64\\lib\\gcc\\x86_64-w64-mingw32\\11.2.0\\include\\c++\\backward","-isystem","C:\\Qt\\Tools\\QtCreator\\bin\\clang\\lib\\clang\\15.0.0\\include","-isystem","C:\\Qt\\Tools\\mingw1120_64\\x86_64-w64-mingw32\\include","-fmessage-length=0","-fdiagnostics-show-note-include-stack","-fretain-comments-from-system-headers","-fmacro-backtrace-limit=0","-ferror-limit=1000","-x","c++-header","D:\\qt\\qt\\STO2\\ordersadd.h"],"directory":"D:/qt/qt/STO2/.qtc_clangd","file":"D:/qt/qt/STO2/ordersadd.h"},{"arguments":["clang","-Wno-documentation-unknown-command","-Wno-unknown-warning-option","-Wno-unknown-pragmas","-nostdinc","-nostdinc++","-std=gnu++1z","-Wall","-Wextra","-Wextra","-fexceptions","-mthreads","-fsyntax-only","-m64","--target=x86_64-w64-mingw32","-DUNICODE","-D_UNICODE","-DWIN32","-DMINGW_HAS_SECURE_API","-DQT_NO_DEBUG","-DQT_PRINTSUPPORT_LIB","-DQT_CHARTS_LIB","-DQT_OPENGLWIDGETS_LIB","-DQT_WIDGETS_LIB","-DQT_OPENGL_LIB","-DQT_GUI_LIB","-DQT_SQL_LIB","-DQT_CORE_LIB","-DQT_NEEDS_QMAIN","-DQ_CREATOR_RUN","-IC:\\Qt\\Tools\\QtCreator\\share\\qtcreator\\cplusplus\\wrappedMingwHeaders","-IC:\\Qt\\Tools\\QtCreator\\share\\qtcreator\\cplusplus\\wrappedQtHeaders","-IC:\\Qt\\Tools\\QtCreator\\share\\qtcreator\\cplusplus\\wrappedQtHeaders\\QtCore","-ID:\\qt\\qt\\STO2","-IC:\\Qt\\6.4.1\\mingw_64\\include","-IC:\\Qt\\6.4.1\\mingw_64\\include\\QtPrintSupport","-IC:\\Qt\\6.4.1\\mingw_64\\include\\QtCharts","-IC:\\Qt\\6.4.1\\mingw_64\\include\\QtOpenGLWidgets","-IC:\\Qt\\6.4.1\\mingw_64\\include\\QtWidgets","-IC:\\Qt\\6.4.1\\mingw_64\\include\\QtOpenGL","-IC:\\Qt\\6.4.1\\mingw_64\\include\\QtGui","-IC:\\Qt\\6.4.1\\mingw_64\\include\\QtSql","-IC:\\Qt\\6.4.1\\mingw_64\\include\\QtCore","-ID:\\qt\\qt\\STO2\\release","-IC:\\Qt\\6.4.1\\mingw_64\\mkspecs\\win32-g++","-isystem","C:\\Qt\\Tools\\mingw1120_64\\lib\\gcc\\x86_64-w64-mingw32\\11.2.0\\include\\c++","-isystem","C:\\Qt\\Tools\\mingw1120_64\\lib\\gcc\\x86_64-w64-mingw32\\11.2.0\\include\\c++\\x86_64-w64-mingw32","-isystem","C:\\Qt\\Tools\\mingw1120_64\\lib\\gcc\\x86_64-w64-mingw32\\11.2.0\\include\\c++\\backward","-isystem","C:\\Qt\\Tools\\QtCreator\\bin\\clang\\lib\\clang\\15.0.0\\include","-isystem","C:\\Qt\\Tools\\mingw1120_64\\x86_64-w64-mingw32\\include","-fmessage-length=0","-fdiagnostics-show-note-include-stack","-fretain-comments-from-system-headers","-fmacro-backtrace-limit=0","-ferror-limit=1000","-x","c++-header","D:\\qt\\qt\\STO2\\partsalesadd.h"],"directory":"D:/qt/qt/STO2/.qtc_clangd","file":"D:/qt/qt/STO2/partsalesadd.h"},{"arguments":["clang","-Wno-documentation-unknown-command","-Wno-unknown-warning-option","-Wno-unknown-pragmas","-nostdinc","-nostdinc++","-std=gnu++1z","-Wall","-Wextra","-Wextra","-fexceptions","-mthreads","-fsyntax-only","-m64","--target=x86_64-w64-mingw32","-DUNICODE","-D_UNICODE","-DWIN32","-DMINGW_HAS_SECURE_API","-DQT_NO_DEBUG","-DQT_PRINTSUPPORT_LIB","-DQT_CHARTS_LIB","-DQT_OPENGLWIDGETS_LIB","-DQT_WIDGETS_LIB","-DQT_OPENGL_LIB","-DQT_GUI_LIB","-DQT_SQL_LIB","-DQT_CORE_LIB","-DQT_NEEDS_QMAIN","-DQ_CREATOR_RUN","-IC:\\Qt\\Tools\\QtCreator\\share\\qtcreator\\cplusplus\\wrappedMingwHeaders","-IC:\\Qt\\Tools\\QtCreator\\share\\qtcreator\\cplusplus\\wrappedQtHeaders","-IC:\\Qt\\Tools\\QtCreator\\share\\qtcreator\\cplusplus\\wrappedQtHeaders\\QtCore","-ID:\\qt\\qt\\STO2","-IC:\\Qt\\6.4.1\\mingw_64\\include","-IC:\\Qt\\6.4.1\\mingw_64\\include\\QtPrintSupport","-IC:\\Qt\\6.4.1\\mingw_64\\include\\QtCharts","-IC:\\Qt\\6.4.1\\mingw_64\\include\\QtOpenGLWidgets","-IC:\\Qt\\6.4.1\\mingw_64\\include\\QtWidgets","-IC:\\Qt\\6.4.1\\mingw_64\\include\\QtOpenGL","-IC:\\Qt\\6.4.1\\mingw_64\\include\\QtGui","-IC:\\Qt\\6.4.1\\mingw_64\\include\\QtSql","-IC:\\Qt\\6.4.1\\mingw_64\\include\\QtCore","-ID:\\qt\\qt\\STO2\\release","-IC:\\Qt\\6.4.1\\mingw_64\\mkspecs\\win32-g++","-isystem","C:\\Qt\\Tools\\mingw1120_64\\lib\\gcc\\x86_64-w64-mingw32\\11.2.0\\include\\c++","-isystem","C:\\Qt\\Tools\\mingw1120_64\\lib\\gcc\\x86_64-w64-mingw32\\11.2.0\\include\\c++\\x86_64-w64-mingw32","-isystem","C:\\Qt\\Tools\\mingw1120_64\\lib\\gcc\\x86_64-w64-mingw32\\11.2.0\\include\\c++\\backward","-isystem","C:\\Qt\\Tools\\QtCreator\\bin\\clang\\lib\\clang\\15.0.0\\include","-isystem","C:\\Qt\\Tools\\mingw1120_64\\x86_64-w64-mingw32\\include","-fmessage-length=0","-fdiagnostics-show-note-include-stack","-fretain-comments-from-system-headers","-fmacro-backtrace-limit=0","-ferror-limit=1000","-x","c++-header","D:\\qt\\qt\\STO2\\rempogar.h"],"directory":"D:/qt/qt/STO2/.qtc_clangd","file":"D:/qt/qt/STO2/rempogar.h"},{"arguments":["clang","-Wno-documentation-unknown-command","-Wno-unknown-warning-option","-Wno-unknown-pragmas","-nostdinc","-nostdinc++","-std=gnu++1z","-Wall","-Wextra","-Wextra","-fexceptions","-mthreads","-fsyntax-only","-m64","--target=x86_64-w64-mingw32","-DUNICODE","-D_UNICODE","-DWIN32","-DMINGW_HAS_SECURE_API","-DQT_NO_DEBUG","-DQT_PRINTSUPPORT_LIB","-DQT_CHARTS_LIB","-DQT_OPENGLWIDGETS_LIB","-DQT_WIDGETS_LIB","-DQT_OPENGL_LIB","-DQT_GUI_LIB","-DQT_SQL_LIB","-DQT_CORE_LIB","-DQT_NEEDS_QMAIN","-DQ_CREATOR_RUN","-IC:\\Qt\\Tools\\QtCreator\\share\\qtcreator\\cplusplus\\wrappedMingwHeaders","-IC:\\Qt\\Tools\\QtCreator\\share\\qtcreator\\cplusplus\\wrappedQtHeaders","-IC:\\Qt\\Tools\\QtCreator\\share\\qtcreator\\cplusplus\\wrappedQtHeaders\\QtCore","-ID:\\qt\\qt\\STO2","-IC:\\Qt\\6.4.1\\mingw_64\\include","-IC:\\Qt\\6.4.1\\mingw_64\\include\\QtPrintSupport","-IC:\\Qt\\6.4.1\\mingw_64\\include\\QtCharts","-IC:\\Qt\\6.4.1\\mingw_64\\include\\QtOpenGLWidgets","-IC:\\Qt\\6.4.1\\mingw_64\\include\\QtWidgets","-IC:\\Qt\\6.4.1\\mingw_64\\include\\QtOpenGL","-IC:\\Qt\\6.4.1\\mingw_64\\include\\QtGui","-IC:\\Qt\\6.4.1\\mingw_64\\include\\QtSql","-IC:\\Qt\\6.4.1\\mingw_64\\include\\QtCore","-ID:\\qt\\qt\\STO2\\release","-IC:\\Qt\\6.4.1\\mingw_64\\mkspecs\\win32-g++","-isystem","C:\\Qt\\Tools\\mingw1120_64\\lib\\gcc\\x86_64-w64-mingw32\\11.2.0\\include\\c++","-isystem","C:\\Qt\\Tools\\mingw1120_64\\lib\\gcc\\x86_64-w64-mingw32\\11.2.0\\include\\c++\\x86_64-w64-mingw32","-isystem","C:\\Qt\\Tools\\mingw1120_64\\lib\\gcc\\x86_64-w64-mingw32\\11.2.0\\include\\c++\\backward","-isystem","C:\\Qt\\Tools\\QtCreator\\bin\\clang\\lib\\clang\\15.0.0\\include","-isystem","C:\\Qt\\Tools\\mingw1120_64\\x86_64-w64-mingw32\\include","-fmessage-length=0","-fdiagnostics-show-note-include-stack","-fretain-comments-from-system-headers","-fmacro-backtrace-limit=0","-ferror-limit=1000","-x","c++-header","D:\\qt\\qt\\STO2\\reviews.h"],"directory":"D:/qt/qt/STO2/.qtc_clangd","file":"D:/qt/qt/STO2/reviews.h"},{"arguments":["clang","-Wno-documentation-unknown-command","-Wno-unknown-warning-option","-Wno-unknown-pragmas","-nostdinc","-nostdinc++","-std=gnu++1z","-Wall","-Wextra","-Wextra","-fexceptions","-mthreads","-fsyntax-only","-m64","--target=x86_64-w64-mingw32","-DUNICODE","-D_UNICODE","-DWIN32","-DMINGW_HAS_SECURE_API","-DQT_NO_DEBUG","-DQT_PRINTSUPPORT_LIB","-DQT_CHARTS_LIB","-DQT_OPENGLWIDGETS_LIB","-DQT_WIDGETS_LIB","-DQT_OPENGL_LIB","-DQT_GUI_LIB","-DQT_SQL_LIB","-DQT_CORE_LIB","-DQT_NEEDS_QMAIN","-DQ_CREATOR_RUN","-IC:\\Qt\\Tools\\QtCreator\\share\\qtcreator\\cplusplus\\wrappedMingwHeaders","-IC:\\Qt\\Tools\\QtCreator\\share\\qtcreator\\cplusplus\\wrappedQtHeaders","-IC:\\Qt\\Tools\\QtCreator\\share\\qtcreator\\cplusplus\\wrappedQtHeaders\\QtCore","-ID:\\qt\\qt\\STO2","-IC:\\Qt\\6.4.1\\mingw_64\\include","-IC:\\Qt\\6.4.1\\mingw_64\\include\\QtPrintSupport","-IC:\\Qt\\6.4.1\\mingw_64\\include\\QtCharts","-IC:\\Qt\\6.4.1\\mingw_64\\include\\QtOpenGLWidgets","-IC:\\Qt\\6.4.1\\mingw_64\\include\\QtWidgets","-IC:\\Qt\\6.4.1\\mingw_64\\include\\QtOpenGL","-IC:\\Qt\\6.4.1\\mingw_64\\include\\QtGui","-IC:\\Qt\\6.4.1\\mingw_64\\include\\QtSql","-IC:\\Qt\\6.4.1\\mingw_64\\include\\QtCore","-ID:\\qt\\qt\\STO2\\release","-IC:\\Qt\\6.4.1\\mingw_64\\mkspecs\\win32-g++","-isystem","C:\\Qt\\Tools\\mingw1120_64\\lib\\gcc\\x86_64-w64-mingw32\\11.2.0\\include\\c++","-isystem","C:\\Qt\\Tools\\mingw1120_64\\lib\\gcc\\x86_64-w64-mingw32\\11.2.0\\include\\c++\\x86_64-w64-mingw32","-isystem","C:\\Qt\\Tools\\mingw1120_64\\lib\\gcc\\x86_64-w64-mingw32\\11.2.0\\include\\c++\\backward","-isystem","C:\\Qt\\Tools\\QtCreator\\bin\\clang\\lib\\clang\\15.0.0\\include","-isystem","C:\\Qt\\Tools\\mingw1120_64\\x86_64-w64-mingw32\\include","-fmessage-length=0","-fdiagnostics-show-note-include-stack","-fretain-comments-from-system-headers","-fmacro-backtrace-limit=0","-ferror-limit=1000","-x","c++-header","D:\\qt\\qt\\STO2\\servicesadd.h"],"directory":"D:/qt/qt/STO2/.qtc_clangd","file":"D:/qt/qt/STO2/servicesadd.h"},{"arguments":["clang","-Wno-documentation-unknown-command","-Wno-unknown-warning-option","-Wno-unknown-pragmas","-nostdinc","-nostdinc++","-std=gnu++1z","-Wall","-Wextra","-Wextra","-fexceptions","-mthreads","-fsyntax-only","-m64","--target=x86_64-w64-mingw32","-DUNICODE","-D_UNICODE","-DWIN32","-DMINGW_HAS_SECURE_API","-DQT_NO_DEBUG","-DQT_PRINTSUPPORT_LIB","-DQT_CHARTS_LIB","-DQT_OPENGLWIDGETS_LIB","-DQT_WIDGETS_LIB","-DQT_OPENGL_LIB","-DQT_GUI_LIB","-DQT_SQL_LIB","-DQT_CORE_LIB","-DQT_NEEDS_QMAIN","-DQ_CREATOR_RUN","-IC:\\Qt\\Tools\\QtCreator\\share\\qtcreator\\cplusplus\\wrappedMingwHeaders","-IC:\\Qt\\Tools\\QtCreator\\share\\qtcreator\\cplusplus\\wrappedQtHeaders","-IC:\\Qt\\Tools\\QtCreator\\share\\qtcreator\\cplusplus\\wrappedQtHeaders\\QtCore","-ID:\\qt\\qt\\STO2","-IC:\\Qt\\6.4.1\\mingw_64\\include","-IC:\\Qt\\6.4.1\\mingw_64\\include\\QtPrintSupport","-IC:\\Qt\\6.4.1\\mingw_64\\include\\QtCharts","-IC:\\Qt\\6.4.1\\mingw_64\\include\\QtOpenGLWidgets","-IC:\\Qt\\6.4.1\\mingw_64\\include\\QtWidgets","-IC:\\Qt\\6.4.1\\mingw_64\\include\\QtOpenGL","-IC:\\Qt\\6.4.1\\mingw_64\\include\\QtGui","-IC:\\Qt\\6.4.1\\mingw_64\\include\\QtSql","-IC:\\Qt\\6.4.1\\mingw_64\\include\\QtCore","-ID:\\qt\\qt\\STO2\\release","-IC:\\Qt\\6.4.1\\mingw_64\\mkspecs\\win32-g++","-isystem","C:\\Qt\\Tools\\mingw1120_64\\lib\\gcc\\x86_64-w64-mingw32\\11.2.0\\include\\c++","-isystem","C:\\Qt\\Tools\\mingw1120_64\\lib\\gcc\\x86_64-w64-mingw32\\11.2.0\\include\\c++\\x86_64-w64-mingw32","-isystem","C:\\Qt\\Tools\\mingw1120_64\\lib\\gcc\\x86_64-w64-mingw32\\11.2.0\\include\\c++\\backward","-isystem","C:\\Qt\\Tools\\QtCreator\\bin\\clang\\lib\\clang\\15.0.0\\include","-isystem","C:\\Qt\\Tools\\mingw1120_64\\x86_64-w64-mingw32\\include","-fmessage-length=0","-fdiagnostics-show-note-include-stack","-fretain-comments-from-system-headers","-fmacro-backtrace-limit=0","-ferror-limit=1000","-x","c++-header","D:\\qt\\qt\\STO2\\sparapartsadd.h"],"directory":"D:/qt/qt/STO2/.qtc_clangd","file":"D:/qt/qt/STO2/sparapartsadd.h"},{"arguments":["clang","-Wno-documentation-unknown-command","-Wno-unknown-warning-option","-Wno-unknown-pragmas","-nostdinc","-nostdinc++","-std=gnu++1z","-Wall","-Wextra","-Wextra","-fexceptions","-mthreads","-fsyntax-only","-m64","--target=x86_64-w64-mingw32","-DUNICODE","-D_UNICODE","-DWIN32","-DMINGW_HAS_SECURE_API","-DQT_NO_DEBUG","-DQT_PRINTSUPPORT_LIB","-DQT_CHARTS_LIB","-DQT_OPENGLWIDGETS_LIB","-DQT_WIDGETS_LIB","-DQT_OPENGL_LIB","-DQT_GUI_LIB","-DQT_SQL_LIB","-DQT_CORE_LIB","-DQT_NEEDS_QMAIN","-DQ_CREATOR_RUN","-IC:\\Qt\\Tools\\QtCreator\\share\\qtcreator\\cplusplus\\wrappedMingwHeaders","-IC:\\Qt\\Tools\\QtCreator\\share\\qtcreator\\cplusplus\\wrappedQtHeaders","-IC:\\Qt\\Tools\\QtCreator\\share\\qtcreator\\cplusplus\\wrappedQtHeaders\\QtCore","-ID:\\qt\\qt\\STO2","-IC:\\Qt\\6.4.1\\mingw_64\\include","-IC:\\Qt\\6.4.1\\mingw_64\\include\\QtPrintSupport","-IC:\\Qt\\6.4.1\\mingw_64\\include\\QtCharts","-IC:\\Qt\\6.4.1\\mingw_64\\include\\QtOpenGLWidgets","-IC:\\Qt\\6.4.1\\mingw_64\\include\\QtWidgets","-IC:\\Qt\\6.4.1\\mingw_64\\include\\QtOpenGL","-IC:\\Qt\\6.4.1\\mingw_64\\include\\QtGui","-IC:\\Qt\\6.4.1\\mingw_64\\include\\QtSql","-IC:\\Qt\\6.4.1\\mingw_64\\include\\QtCore","-ID:\\qt\\qt\\STO2\\release","-IC:\\Qt\\6.4.1\\mingw_64\\mkspecs\\win32-g++","-isystem","C:\\Qt\\Tools\\mingw1120_64\\lib\\gcc\\x86_64-w64-mingw32\\11.2.0\\include\\c++","-isystem","C:\\Qt\\Tools\\mingw1120_64\\lib\\gcc\\x86_64-w64-mingw32\\11.2.0\\include\\c++\\x86_64-w64-mingw32","-isystem","C:\\Qt\\Tools\\mingw1120_64\\lib\\gcc\\x86_64-w64-mingw32\\11.2.0\\include\\c++\\backward","-isystem","C:\\Qt\\Tools\\QtCreator\\bin\\clang\\lib\\clang\\15.0.0\\include","-isystem","C:\\Qt\\Tools\\mingw1120_64\\x86_64-w64-mingw32\\include","-fmessage-length=0","-fdiagnostics-show-note-include-stack","-fretain-comments-from-system-headers","-fmacro-backtrace-limit=0","-ferror-limit=1000","-x","c++-header","D:\\qt\\qt\\STO2\\staffadd.h"],"directory":"D:/qt/qt/STO2/.qtc_clangd","file":"D:/qt/qt/STO2/staffadd.h"},{"arguments":["clang","-Wno-documentation-unknown-command","-Wno-unknown-warning-option","-Wno-unknown-pragmas","-nostdinc","-nostdinc++","-std=gnu++1z","-Wall","-Wextra","-Wextra","-fexceptions","-mthreads","-fsyntax-only","-m64","--target=x86_64-w64-mingw32","-DUNICODE","-D_UNICODE","-DWIN32","-DMINGW_HAS_SECURE_API","-DQT_NO_DEBUG","-DQT_PRINTSUPPORT_LIB","-DQT_CHARTS_LIB","-DQT_OPENGLWIDGETS_LIB","-DQT_WIDGETS_LIB","-DQT_OPENGL_LIB","-DQT_GUI_LIB","-DQT_SQL_LIB","-DQT_CORE_LIB","-DQT_NEEDS_QMAIN","-DQ_CREATOR_RUN","-IC:\\Qt\\Tools\\QtCreator\\share\\qtcreator\\cplusplus\\wrappedMingwHeaders","-IC:\\Qt\\Tools\\QtCreator\\share\\qtcreator\\cplusplus\\wrappedQtHeaders","-IC:\\Qt\\Tools\\QtCreator\\share\\qtcreator\\cplusplus\\wrappedQtHeaders\\QtCore","-ID:\\qt\\qt\\STO2","-IC:\\Qt\\6.4.1\\mingw_64\\include","-IC:\\Qt\\6.4.1\\mingw_64\\include\\QtPrintSupport","-IC:\\Qt\\6.4.1\\mingw_64\\include\\QtCharts","-IC:\\Qt\\6.4.1\\mingw_64\\include\\QtOpenGLWidgets","-IC:\\Qt\\6.4.1\\mingw_64\\include\\QtWidgets","-IC:\\Qt\\6.4.1\\mingw_64\\include\\QtOpenGL","-IC:\\Qt\\6.4.1\\mingw_64\\include\\QtGui","-IC:\\Qt\\6.4.1\\mingw_64\\include\\QtSql","-IC:\\Qt\\6.4.1\\mingw_64\\include\\QtCore","-ID:\\qt\\qt\\STO2\\release","-IC:\\Qt\\6.4.1\\mingw_64\\mkspecs\\win32-g++","-isystem","C:\\Qt\\Tools\\mingw1120_64\\lib\\gcc\\x86_64-w64-mingw32\\11.2.0\\include\\c++","-isystem","C:\\Qt\\Tools\\mingw1120_64\\lib\\gcc\\x86_64-w64-mingw32\\11.2.0\\include\\c++\\x86_64-w64-mingw32","-isystem","C:\\Qt\\Tools\\mingw1120_64\\lib\\gcc\\x86_64-w64-mingw32\\11.2.0\\include\\c++\\backward","-isystem","C:\\Qt\\Tools\\QtCreator\\bin\\clang\\lib\\clang\\15.0.0\\include","-isystem","C:\\Qt\\Tools\\mingw1120_64\\x86_64-w64-mingw32\\include","-fmessage-length=0","-fdiagnostics-show-note-include-stack","-fretain-comments-from-system-headers","-fmacro-backtrace-limit=0","-ferror-limit=1000","-x","c++-header","D:\\qt\\qt\\STO2\\viewtablesto.h"],"directory":"D:/qt/qt/STO2/.qtc_clangd","file":"D:/qt/qt/STO2/viewtablesto.h"},{"arguments":["clang","-Wno-documentation-unknown-command","-Wno-unknown-warning-option","-Wno-unknown-pragmas","-nostdinc","-nostdinc++","-std=gnu++1z","-Wall","-Wextra","-Wextra","-fexceptions","-mthreads","-fsyntax-only","-m64","--target=x86_64-w64-mingw32","-DUNICODE","-D_UNICODE","-DWIN32","-DMINGW_HAS_SECURE_API","-DQT_NO_DEBUG","-DQT_PRINTSUPPORT_LIB","-DQT_CHARTS_LIB","-DQT_OPENGLWIDGETS_LIB","-DQT_WIDGETS_LIB","-DQT_OPENGL_LIB","-DQT_GUI_LIB","-DQT_SQL_LIB","-DQT_CORE_LIB","-DQT_NEEDS_QMAIN","-DQ_CREATOR_RUN","-IC:\\Qt\\Tools\\QtCreator\\share\\qtcreator\\cplusplus\\wrappedMingwHeaders","-IC:\\Qt\\Tools\\QtCreator\\share\\qtcreator\\cplusplus\\wrappedQtHeaders","-IC:\\Qt\\Tools\\QtCreator\\share\\qtcreator\\cplusplus\\wrappedQtHeaders\\QtCore","-ID:\\qt\\qt\\STO2","-IC:\\Qt\\6.4.1\\mingw_64\\include","-IC:\\Qt\\6.4.1\\mingw_64\\include\\QtPrintSupport","-IC:\\Qt\\6.4.1\\mingw_64\\include\\QtCharts","-IC:\\Qt\\6.4.1\\mingw_64\\include\\QtOpenGLWidgets","-IC:\\Qt\\6.4.1\\mingw_64\\include\\QtWidgets","-IC:\\Qt\\6.4.1\\mingw_64\\include\\QtOpenGL","-IC:\\Qt\\6.4.1\\mingw_64\\include\\QtGui","-IC:\\Qt\\6.4.1\\mingw_64\\include\\QtSql","-IC:\\Qt\\6.4.1\\mingw_64\\include\\QtCore","-ID:\\qt\\qt\\STO2\\release","-IC:\\Qt\\6.4.1\\mingw_64\\mkspecs\\win32-g++","-isystem","C:\\Qt\\Tools\\mingw1120_64\\lib\\gcc\\x86_64-w64-mingw32\\11.2.0\\include\\c++","-isystem","C:\\Qt\\Tools\\mingw1120_64\\lib\\gcc\\x86_64-w64-mingw32\\11.2.0\\include\\c++\\x86_64-w64-mingw32","-isystem","C:\\Qt\\Tools\\mingw1120_64\\lib\\gcc\\x86_64-w64-mingw32\\11.2.0\\include\\c++\\backward","-isystem","C:\\Qt\\Tools\\QtCreator\\bin\\clang\\lib\\clang\\15.0.0\\include","-isystem","C:\\Qt\\Tools\\mingw1120_64\\x86_64-w64-mingw32\\include","-fmessage-length=0","-fdiagnostics-show-note-include-stack","-fretain-comments-from-system-headers","-fmacro-backtrace-limit=0","-ferror-limit=1000","-x","c++-header","D:\\qt\\qt\\STO2\\warrantycasesadd.h"],"directory":"D:/qt/qt/STO2/.qtc_clangd","file":"D:/qt/qt/STO2/warrantycasesadd.h"},{"arguments":["clang","-Wno-documentation-unknown-command","-Wno-unknown-warning-option","-Wno-unknown-pragmas","-nostdinc","-nostdinc++","-std=gnu++1z","-Wall","-Wextra","-Wextra","-fexceptions","-mthreads","-fsyntax-only","-m64","--target=x86_64-w64-mingw32","-DUNICODE","-D_UNICODE","-DWIN32","-DMINGW_HAS_SECURE_API","-DQT_NO_DEBUG","-DQT_PRINTSUPPORT_LIB","-DQT_CHARTS_LIB","-DQT_OPENGLWIDGETS_LIB","-DQT_WIDGETS_LIB","-DQT_OPENGL_LIB","-DQT_GUI_LIB","-DQT_SQL_LIB","-DQT_CORE_LIB","-DQT_NEEDS_QMAIN","-DQ_CREATOR_RUN","-IC:\\Qt\\Tools\\QtCreator\\share\\qtcreator\\cplusplus\\wrappedMingwHeaders","-IC:\\Qt\\Tools\\QtCreator\\share\\qtcreator\\cplusplus\\wrappedQtHeaders","-IC:\\Qt\\Tools\\QtCreator\\share\\qtcreator\\cplusplus\\wrappedQtHeaders\\QtCore","-ID:\\qt\\qt\\STO2","-IC:\\Qt\\6.4.1\\mingw_64\\include","-IC:\\Qt\\6.4.1\\mingw_64\\include\\QtPrintSupport","-IC:\\Qt\\6.4.1\\mingw_64\\include\\QtCharts","-IC:\\Qt\\6.4.1\\mingw_64\\include\\QtOpenGLWidgets","-IC:\\Qt\\6.4.1\\mingw_64\\include\\QtWidgets","-IC:\\Qt\\6.4.1\\mingw_64\\include\\QtOpenGL","-IC:\\Qt\\6.4.1\\mingw_64\\include\\QtGui","-IC:\\Qt\\6.4.1\\mingw_64\\include\\QtSql","-IC:\\Qt\\6.4.1\\mingw_64\\include\\QtCore","-ID:\\qt\\qt\\STO2\\release","-IC:\\Qt\\6.4.1\\mingw_64\\mkspecs\\win32-g++","-isystem","C:\\Qt\\Tools\\mingw1120_64\\lib\\gcc\\x86_64-w64-mingw32\\11.2.0\\include\\c++","-isystem","C:\\Qt\\Tools\\mingw1120_64\\lib\\gcc\\x86_64-w64-mingw32\\11.2.0\\include\\c++\\x86_64-w64-mingw32","-isystem","C:\\Qt\\Tools\\mingw1120_64\\lib\\gcc\\x86_64-w64-mingw32\\11.2.0\\include\\c++\\backward","-isystem","C:\\Qt\\Tools\\QtCreator\\bin\\clang\\lib\\clang\\15.0.0\\include","-isystem","C:\\Qt\\Tools\\mingw1120_64\\x86_64-w64-mingw32\\include","-fmessage-length=0","-fdiagnostics-show-note-include-stack","-fretain-comments-from-system-headers","-fmacro-backtrace-limit=0","-ferror-limit=1000","-x","c++-header","D:\\qt\\qt\\STO2\\warrantyrepairsadd.h"],"directory":"D:/qt/qt/STO2/.qtc_clangd","file":"D:/qt/qt/STO2/warrantyrepairsadd.h"},{"arguments":["clang","-Wno-documentation-unknown-command","-Wno-unknown-warning-option","-Wno-unknown-pragmas","-nostdinc","-nostdinc++","-std=gnu++1z","-Wall","-Wextra","-Wextra","-fexceptions","-mthreads","-fsyntax-only","-m64","--target=x86_64-w64-mingw32","-DUNICODE","-D_UNICODE","-DWIN32","-DMINGW_HAS_SECURE_API","-DQT_NO_DEBUG","-DQT_PRINTSUPPORT_LIB","-DQT_CHARTS_LIB","-DQT_OPENGLWIDGETS_LIB","-DQT_WIDGETS_LIB","-DQT_OPENGL_LIB","-DQT_GUI_LIB","-DQT_SQL_LIB","-DQT_CORE_LIB","-DQT_NEEDS_QMAIN","-DQ_CREATOR_RUN","-IC:\\Qt\\Tools\\QtCreator\\share\\qtcreator\\cplusplus\\wrappedMingwHeaders","-IC:\\Qt\\Tools\\QtCreator\\share\\qtcreator\\cplusplus\\wrappedQtHeaders","-IC:\\Qt\\Tools\\QtCreator\\share\\qtcreator\\cplusplus\\wrappedQtHeaders\\QtCore","-ID:\\qt\\qt\\STO2","-IC:\\Qt\\6.4.1\\mingw_64\\include","-IC:\\Qt\\6.4.1\\mingw_64\\include\\QtPrintSupport","-IC:\\Qt\\6.4.1\\mingw_64\\include\\QtCharts","-IC:\\Qt\\6.4.1\\mingw_64\\include\\QtOpenGLWidgets","-IC:\\Qt\\6.4.1\\mingw_64\\include\\QtWidgets","-IC:\\Qt\\6.4.1\\mingw_64\\include\\QtOpenGL","-IC:\\Qt\\6.4.1\\mingw_64\\include\\QtGui","-IC:\\Qt\\6.4.1\\mingw_64\\include\\QtSql","-IC:\\Qt\\6.4.1\\mingw_64\\include\\QtCore","-ID:\\qt\\qt\\STO2\\release","-IC:\\Qt\\6.4.1\\mingw_64\\mkspecs\\win32-g++","-isystem","C:\\Qt\\Tools\\mingw1120_64\\lib\\gcc\\x86_64-w64-mingw32\\11.2.0\\include\\c++","-isystem","C:\\Qt\\Tools\\mingw1120_64\\lib\\gcc\\x86_64-w64-mingw32\\11.2.0\\include\\c++\\x86_64-w64-mingw32","-isystem","C:\\Qt\\Tools\\mingw1120_64\\lib\\gcc\\x86_64-w64-mingw32\\11.2.0\\include\\c++\\backward","-isystem","C:\\Qt\\Tools\\QtCreator\\bin\\clang\\lib\\clang\\15.0.0\\include","-isystem","C:\\Qt\\Tools\\mingw1120_64\\x86_64-w64-mingw32\\include","-fmessage-length=0","-fdiagnostics-show-note-include-stack","-fretain-comments-from-system-headers","-fmacro-backtrace-limit=0","-ferror-limit=1000","-x","c++-header","D:\\qt\\qt\\STO2\\warsot.h"],"directory":"D:/qt/qt/STO2/.qtc_clangd","file":"D:/qt/qt/STO2/warsot.h"},{"arguments":["clang","-Wno-documentation-unknown-command","-Wno-unknown-warning-option","-Wno-unknown-pragmas","-nostdinc","-nostdinc++","-std=gnu++1z","-Wall","-Wextra","-Wextra","-fexceptions","-mthreads","-fsyntax-only","-m64","--target=x86_64-w64-mingw32","-DUNICODE","-D_UNICODE","-DWIN32","-DMINGW_HAS_SECURE_API","-DQT_NO_DEBUG","-DQT_PRINTSUPPORT_LIB","-DQT_CHARTS_LIB","-DQT_OPENGLWIDGETS_LIB","-DQT_WIDGETS_LIB","-DQT_OPENGL_LIB","-DQT_GUI_LIB","-DQT_SQL_LIB","-DQT_CORE_LIB","-DQT_NEEDS_QMAIN","-DQ_CREATOR_RUN","-IC:\\Qt\\Tools\\QtCreator\\share\\qtcreator\\cplusplus\\wrappedMingwHeaders","-IC:\\Qt\\Tools\\QtCreator\\share\\qtcreator\\cplusplus\\wrappedQtHeaders","-IC:\\Qt\\Tools\\QtCreator\\share\\qtcreator\\cplusplus\\wrappedQtHeaders\\QtCore","-ID:\\qt\\qt\\STO2","-IC:\\Qt\\6.4.1\\mingw_64\\include","-IC:\\Qt\\6.4.1\\mingw_64\\include\\QtPrintSupport","-IC:\\Qt\\6.4.1\\mingw_64\\include\\QtCharts","-IC:\\Qt\\6.4.1\\mingw_64\\include\\QtOpenGLWidgets","-IC:\\Qt\\6.4.1\\mingw_64\\include\\QtWidgets","-IC:\\Qt\\6.4.1\\mingw_64\\include\\QtOpenGL","-IC:\\Qt\\6.4.1\\mingw_64\\include\\QtGui","-IC:\\Qt\\6.4.1\\mingw_64\\include\\QtSql","-IC:\\Qt\\6.4.1\\mingw_64\\include\\QtCore","-ID:\\qt\\qt\\STO2\\release","-IC:\\Qt\\6.4.1\\mingw_64\\mkspecs\\win32-g++","-isystem","C:\\Qt\\Tools\\mingw1120_64\\lib\\gcc\\x86_64-w64-mingw32\\11.2.0\\include\\c++","-isystem","C:\\Qt\\Tools\\mingw1120_64\\lib\\gcc\\x86_64-w64-mingw32\\11.2.0\\include\\c++\\x86_64-w64-mingw32","-isystem","C:\\Qt\\Tools\\mingw1120_64\\lib\\gcc\\x86_64-w64-mingw32\\11.2.0\\include\\c++\\backward","-isystem","C:\\Qt\\Tools\\QtCreator\\bin\\clang\\lib\\clang\\15.0.0\\include","-isystem","C:\\Qt\\Tools\\mingw1120_64\\x86_64-w64-mingw32\\include","-fmessage-length=0","-fdiagnostics-show-note-include-stack","-fretain-comments-from-system-headers","-fmacro-backtrace-limit=0","-ferror-limit=1000","-x","c++-header","D:\\qt\\qt\\STO2\\workshuduleadd.h"],"directory":"D:/qt/qt/STO2/.qtc_clangd","file":"D:/qt/qt/STO2/workshuduleadd.h"},{"arguments":["clang","-Wno-documentation-unknown-command","-Wno-unknown-warning-option","-Wno-unknown-pragmas","-nostdinc","-nostdinc++","-std=gnu++1z","-Wall","-Wextra","-Wextra","-fexceptions","-mthreads","-fsyntax-only","-m64","--target=x86_64-w64-mingw32","-DUNICODE","-D_UNICODE","-DWIN32","-DMINGW_HAS_SECURE_API","-DQT_NO_DEBUG","-DQT_PRINTSUPPORT_LIB","-DQT_CHARTS_LIB","-DQT_OPENGLWIDGETS_LIB","-DQT_WIDGETS_LIB","-DQT_OPENGL_LIB","-DQT_GUI_LIB","-DQT_SQL_LIB","-DQT_CORE_LIB","-DQT_NEEDS_QMAIN","-DQ_CREATOR_RUN","-IC:\\Qt\\Tools\\QtCreator\\share\\qtcreator\\cplusplus\\wrappedMingwHeaders","-IC:\\Qt\\Tools\\QtCreator\\share\\qtcreator\\cplusplus\\wrappedQtHeaders","-IC:\\Qt\\Tools\\QtCreator\\share\\qtcreator\\cplusplus\\wrappedQtHeaders\\QtCore","-ID:\\qt\\qt\\STO2","-IC:\\Qt\\6.4.1\\mingw_64\\include","-IC:\\Qt\\6.4.1\\mingw_64\\include\\QtPrintSupport","-IC:\\Qt\\6.4.1\\mingw_64\\include\\QtCharts","-IC:\\Qt\\6.4.1\\mingw_64\\include\\QtOpenGLWidgets","-IC:\\Qt\\6.4.1\\mingw_64\\include\\QtWidgets","-IC:\\Qt\\6.4.1\\mingw_64\\include\\QtOpenGL","-IC:\\Qt\\6.4.1\\mingw_64\\include\\QtGui","-IC:\\Qt\\6.4.1\\mingw_64\\include\\QtSql","-IC:\\Qt\\6.4.1\\mingw_64\\include\\QtCore","-ID:\\qt\\qt\\STO2\\release","-IC:\\Qt\\6.4.1\\mingw_64\\mkspecs\\win32-g++","-isystem","C:\\Qt\\Tools\\mingw1120_64\\lib\\gcc\\x86_64-w64-mingw32\\11.2.0\\include\\c++","-isystem","C:\\Qt\\Tools\\mingw1120_64\\lib\\gcc\\x86_64-w64-mingw32\\11.2.0\\include\\c++\\x86_64-w64-mingw32","-isystem","C:\\Qt\\Tools\\mingw1120_64\\lib\\gcc\\x86_64-w64-mingw32\\11.2.0\\include\\c++\\backward","-isystem","C:\\Qt\\Tools\\QtCreator\\bin\\clang\\lib\\clang\\15.0.0\\include","-isystem","C:\\Qt\\Tools\\mingw1120_64\\x86_64-w64-mingw32\\include","-fmessage-length=0","-fdiagnostics-show-note-include-stack","-fretain-comments-from-system-headers","-fmacro-backtrace-limit=0","-ferror-limit=1000","-x","c++-header","D:\\qt\\qt\\STO2\\ui_reviews.h"],"directory":"D:/qt/qt/STO2/.qtc_clangd","file":"D:/qt/qt/STO2/ui_reviews.h"},{"arguments":["clang","-Wno-documentation-unknown-command","-Wno-unknown-warning-option","-Wno-unknown-pragmas","-nostdinc","-nostdinc++","-std=gnu++1z","-Wall","-Wextra","-Wextra","-fexceptions","-mthreads","-fsyntax-only","-m64","--target=x86_64-w64-mingw32","-DUNICODE","-D_UNICODE","-DWIN32","-DMINGW_HAS_SECURE_API","-DQT_NO_DEBUG","-DQT_PRINTSUPPORT_LIB","-DQT_CHARTS_LIB","-DQT_OPENGLWIDGETS_LIB","-DQT_WIDGETS_LIB","-DQT_OPENGL_LIB","-DQT_GUI_LIB","-DQT_SQL_LIB","-DQT_CORE_LIB","-DQT_NEEDS_QMAIN","-DQ_CREATOR_RUN","-IC:\\Qt\\Tools\\QtCreator\\share\\qtcreator\\cplusplus\\wrappedMingwHeaders","-IC:\\Qt\\Tools\\QtCreator\\share\\qtcreator\\cplusplus\\wrappedQtHeaders","-IC:\\Qt\\Tools\\QtCreator\\share\\qtcreator\\cplusplus\\wrappedQtHeaders\\QtCore","-ID:\\qt\\qt\\STO2","-IC:\\Qt\\6.4.1\\mingw_64\\include","-IC:\\Qt\\6.4.1\\mingw_64\\include\\QtPrintSupport","-IC:\\Qt\\6.4.1\\mingw_64\\include\\QtCharts","-IC:\\Qt\\6.4.1\\mingw_64\\include\\QtOpenGLWidgets","-IC:\\Qt\\6.4.1\\mingw_64\\include\\QtWidgets","-IC:\\Qt\\6.4.1\\mingw_64\\include\\QtOpenGL","-IC:\\Qt\\6.4.1\\mingw_64\\include\\QtGui","-IC:\\Qt\\6.4.1\\mingw_64\\include\\QtSql","-IC:\\Qt\\6.4.1\\mingw_64\\include\\QtCore","-ID:\\qt\\qt\\STO2\\release","-IC:\\Qt\\6.4.1\\mingw_64\\mkspecs\\win32-g++","-isystem","C:\\Qt\\Tools\\mingw1120_64\\lib\\gcc\\x86_64-w64-mingw32\\11.2.0\\include\\c++","-isystem","C:\\Qt\\Tools\\mingw1120_64\\lib\\gcc\\x86_64-w64-mingw32\\11.2.0\\include\\c++\\x86_64-w64-mingw32","-isystem","C:\\Qt\\Tools\\mingw1120_64\\lib\\gcc\\x86_64-w64-mingw32\\11.2.0\\include\\c++\\backward","-isystem","C:\\Qt\\Tools\\QtCreator\\bin\\clang\\lib\\clang\\15.0.0\\include","-isystem","C:\\Qt\\Tools\\mingw1120_64\\x86_64-w64-mingw32\\include","-fmessage-length=0","-fdiagnostics-show-note-include-stack","-fretain-comments-from-system-headers","-fmacro-backtrace-limit=0","-ferror-limit=1000","-x","c++-header","D:\\qt\\qt\\STO2\\ui_rempogar.h"],"directory":"D:/qt/qt/STO2/.qtc_clangd","file":"D:/qt/qt/STO2/ui_rempogar.h"},{"arguments":["clang","-Wno-documentation-unknown-command","-Wno-unknown-warning-option","-Wno-unknown-pragmas","-nostdinc","-nostdinc++","-std=gnu++1z","-Wall","-Wextra","-Wextra","-fexceptions","-mthreads","-fsyntax-only","-m64","--target=x86_64-w64-mingw32","-DUNICODE","-D_UNICODE","-DWIN32","-DMINGW_HAS_SECURE_API","-DQT_NO_DEBUG","-DQT_PRINTSUPPORT_LIB","-DQT_CHARTS_LIB","-DQT_OPENGLWIDGETS_LIB","-DQT_WIDGETS_LIB","-DQT_OPENGL_LIB","-DQT_GUI_LIB","-DQT_SQL_LIB","-DQT_CORE_LIB","-DQT_NEEDS_QMAIN","-DQ_CREATOR_RUN","-IC:\\Qt\\Tools\\QtCreator\\share\\qtcreator\\cplusplus\\wrappedMingwHeaders","-IC:\\Qt\\Tools\\QtCreator\\share\\qtcreator\\cplusplus\\wrappedQtHeaders","-IC:\\Qt\\Tools\\QtCreator\\share\\qtcreator\\cplusplus\\wrappedQtHeaders\\QtCore","-ID:\\qt\\qt\\STO2","-IC:\\Qt\\6.4.1\\mingw_64\\include","-IC:\\Qt\\6.4.1\\mingw_64\\include\\QtPrintSupport","-IC:\\Qt\\6.4.1\\mingw_64\\include\\QtCharts","-IC:\\Qt\\6.4.1\\mingw_64\\include\\QtOpenGLWidgets","-IC:\\Qt\\6.4.1\\mingw_64\\include\\QtWidgets","-IC:\\Qt\\6.4.1\\mingw_64\\include\\QtOpenGL","-IC:\\Qt\\6.4.1\\mingw_64\\include\\QtGui","-IC:\\Qt\\6.4.1\\mingw_64\\include\\QtSql","-IC:\\Qt\\6.4.1\\mingw_64\\include\\QtCore","-ID:\\qt\\qt\\STO2\\release","-IC:\\Qt\\6.4.1\\mingw_64\\mkspecs\\win32-g++","-isystem","C:\\Qt\\Tools\\mingw1120_64\\lib\\gcc\\x86_64-w64-mingw32\\11.2.0\\include\\c++","-isystem","C:\\Qt\\Tools\\mingw1120_64\\lib\\gcc\\x86_64-w64-mingw32\\11.2.0\\include\\c++\\x86_64-w64-mingw32","-isystem","C:\\Qt\\Tools\\mingw1120_64\\lib\\gcc\\x86_64-w64-mingw32\\11.2.0\\include\\c++\\backward","-isystem","C:\\Qt\\Tools\\QtCreator\\bin\\clang\\lib\\clang\\15.0.0\\include","-isystem","C:\\Qt\\Tools\\mingw1120_64\\x86_64-w64-mingw32\\include","-fmessage-length=0","-fdiagnostics-show-note-include-stack","-fretain-comments-from-system-headers","-fmacro-backtrace-limit=0","-ferror-limit=1000","-x","c++-header","D:\\qt\\qt\\STO2\\ui_warrantycasesadd.h"],"directory":"D:/qt/qt/STO2/.qtc_clangd","file":"D:/qt/qt/STO2/ui_warrantycasesadd.h"},{"arguments":["clang","-Wno-documentation-unknown-command","-Wno-unknown-warning-option","-Wno-unknown-pragmas","-nostdinc","-nostdinc++","-std=gnu++1z","-Wall","-Wextra","-Wextra","-fexceptions","-mthreads","-fsyntax-only","-m64","--target=x86_64-w64-mingw32","-DUNICODE","-D_UNICODE","-DWIN32","-DMINGW_HAS_SECURE_API","-DQT_NO_DEBUG","-DQT_PRINTSUPPORT_LIB","-DQT_CHARTS_LIB","-DQT_OPENGLWIDGETS_LIB","-DQT_WIDGETS_LIB","-DQT_OPENGL_LIB","-DQT_GUI_LIB","-DQT_SQL_LIB","-DQT_CORE_LIB","-DQT_NEEDS_QMAIN","-DQ_CREATOR_RUN","-IC:\\Qt\\Tools\\QtCreator\\share\\qtcreator\\cplusplus\\wrappedMingwHeaders","-IC:\\Qt\\Tools\\QtCreator\\share\\qtcreator\\cplusplus\\wrappedQtHeaders","-IC:\\Qt\\Tools\\QtCreator\\share\\qtcreator\\cplusplus\\wrappedQtHeaders\\QtCore","-ID:\\qt\\qt\\STO2","-IC:\\Qt\\6.4.1\\mingw_64\\include","-IC:\\Qt\\6.4.1\\mingw_64\\include\\QtPrintSupport","-IC:\\Qt\\6.4.1\\mingw_64\\include\\QtCharts","-IC:\\Qt\\6.4.1\\mingw_64\\include\\QtOpenGLWidgets","-IC:\\Qt\\6.4.1\\mingw_64\\include\\QtWidgets","-IC:\\Qt\\6.4.1\\mingw_64\\include\\QtOpenGL","-IC:\\Qt\\6.4.1\\mingw_64\\include\\QtGui","-IC:\\Qt\\6.4.1\\mingw_64\\include\\QtSql","-IC:\\Qt\\6.4.1\\mingw_64\\include\\QtCore","-ID:\\qt\\qt\\STO2\\release","-IC:\\Qt\\6.4.1\\mingw_64\\mkspecs\\win32-g++","-isystem","C:\\Qt\\Tools\\mingw1120_64\\lib\\gcc\\x86_64-w64-mingw32\\11.2.0\\include\\c++","-isystem","C:\\Qt\\Tools\\mingw1120_64\\lib\\gcc\\x86_64-w64-mingw32\\11.2.0\\include\\c++\\x86_64-w64-mingw32","-isystem","C:\\Qt\\Tools\\mingw1120_64\\lib\\gcc\\x86_64-w64-mingw32\\11.2.0\\include\\c++\\backward","-isystem","C:\\Qt\\Tools\\QtCreator\\bin\\clang\\lib\\clang\\15.0.0\\include","-isystem","C:\\Qt\\Tools\\mingw1120_64\\x86_64-w64-mingw32\\include","-fmessage-length=0","-fdiagnostics-show-note-include-stack","-fretain-comments-from-system-headers","-fmacro-backtrace-limit=0","-ferror-limit=1000","-x","c++-header","D:\\qt\\qt\\STO2\\ui_warrantyrepairsadd.h"],"directory":"D:/qt/qt/STO2/.qtc_clangd","file":"D:/qt/qt/STO2/ui_warrantyrepairsadd.h"},{"arguments":["clang","-Wno-documentation-unknown-command","-Wno-unknown-warning-option","-Wno-unknown-pragmas","-nostdinc","-nostdinc++","-std=gnu++1z","-Wall","-Wextra","-Wextra","-fexceptions","-mthreads","-fsyntax-only","-m64","--target=x86_64-w64-mingw32","-DUNICODE","-D_UNICODE","-DWIN32","-DMINGW_HAS_SECURE_API","-DQT_NO_DEBUG","-DQT_PRINTSUPPORT_LIB","-DQT_CHARTS_LIB","-DQT_OPENGLWIDGETS_LIB","-DQT_WIDGETS_LIB","-DQT_OPENGL_LIB","-DQT_GUI_LIB","-DQT_SQL_LIB","-DQT_CORE_LIB","-DQT_NEEDS_QMAIN","-DQ_CREATOR_RUN","-IC:\\Qt\\Tools\\QtCreator\\share\\qtcreator\\cplusplus\\wrappedMingwHeaders","-IC:\\Qt\\Tools\\QtCreator\\share\\qtcreator\\cplusplus\\wrappedQtHeaders","-IC:\\Qt\\Tools\\QtCreator\\share\\qtcreator\\cplusplus\\wrappedQtHeaders\\QtCore","-ID:\\qt\\qt\\STO2","-IC:\\Qt\\6.4.1\\mingw_64\\include","-IC:\\Qt\\6.4.1\\mingw_64\\include\\QtPrintSupport","-IC:\\Qt\\6.4.1\\mingw_64\\include\\QtCharts","-IC:\\Qt\\6.4.1\\mingw_64\\include\\QtOpenGLWidgets","-IC:\\Qt\\6.4.1\\mingw_64\\include\\QtWidgets","-IC:\\Qt\\6.4.1\\mingw_64\\include\\QtOpenGL","-IC:\\Qt\\6.4.1\\mingw_64\\include\\QtGui","-IC:\\Qt\\6.4.1\\mingw_64\\include\\QtSql","-IC:\\Qt\\6.4.1\\mingw_64\\include\\QtCore","-ID:\\qt\\qt\\STO2\\release","-IC:\\Qt\\6.4.1\\mingw_64\\mkspecs\\win32-g++","-isystem","C:\\Qt\\Tools\\mingw1120_64\\lib\\gcc\\x86_64-w64-mingw32\\11.2.0\\include\\c++","-isystem","C:\\Qt\\Tools\\mingw1120_64\\lib\\gcc\\x86_64-w64-mingw32\\11.2.0\\include\\c++\\x86_64-w64-mingw32","-isystem","C:\\Qt\\Tools\\mingw1120_64\\lib\\gcc\\x86_64-w64-mingw32\\11.2.0\\include\\c++\\backward","-isystem","C:\\Qt\\Tools\\QtCreator\\bin\\clang\\lib\\clang\\15.0.0\\include","-isystem","C:\\Qt\\Tools\\mingw1120_64\\x86_64-w64-mingw32\\include","-fmessage-length=0","-fdiagnostics-show-note-include-stack","-fretain-comments-from-system-headers","-fmacro-backtrace-limit=0","-ferror-limit=1000","-x","c++-header","D:\\qt\\qt\\STO2\\ui_clientadd.h"],"directory":"D:/qt/qt/STO2/.qtc_clangd","file":"D:/qt/qt/STO2/ui_clientadd.h"},{"arguments":["clang","-Wno-documentation-unknown-command","-Wno-unknown-warning-option","-Wno-unknown-pragmas","-nostdinc","-nostdinc++","-std=gnu++1z","-Wall","-Wextra","-Wextra","-fexceptions","-mthreads","-fsyntax-only","-m64","--target=x86_64-w64-mingw32","-DUNICODE","-D_UNICODE","-DWIN32","-DMINGW_HAS_SECURE_API","-DQT_NO_DEBUG","-DQT_PRINTSUPPORT_LIB","-DQT_CHARTS_LIB","-DQT_OPENGLWIDGETS_LIB","-DQT_WIDGETS_LIB","-DQT_OPENGL_LIB","-DQT_GUI_LIB","-DQT_SQL_LIB","-DQT_CORE_LIB","-DQT_NEEDS_QMAIN","-DQ_CREATOR_RUN","-IC:\\Qt\\Tools\\QtCreator\\share\\qtcreator\\cplusplus\\wrappedMingwHeaders","-IC:\\Qt\\Tools\\QtCreator\\share\\qtcreator\\cplusplus\\wrappedQtHeaders","-IC:\\Qt\\Tools\\QtCreator\\share\\qtcreator\\cplusplus\\wrappedQtHeaders\\QtCore","-ID:\\qt\\qt\\STO2","-IC:\\Qt\\6.4.1\\mingw_64\\include","-IC:\\Qt\\6.4.1\\mingw_64\\include\\QtPrintSupport","-IC:\\Qt\\6.4.1\\mingw_64\\include\\QtCharts","-IC:\\Qt\\6.4.1\\mingw_64\\include\\QtOpenGLWidgets","-IC:\\Qt\\6.4.1\\mingw_64\\include\\QtWidgets","-IC:\\Qt\\6.4.1\\mingw_64\\include\\QtOpenGL","-IC:\\Qt\\6.4.1\\mingw_64\\include\\QtGui","-IC:\\Qt\\6.4.1\\mingw_64\\include\\QtSql","-IC:\\Qt\\6.4.1\\mingw_64\\include\\QtCore","-ID:\\qt\\qt\\STO2\\release","-IC:\\Qt\\6.4.1\\mingw_64\\mkspecs\\win32-g++","-isystem","C:\\Qt\\Tools\\mingw1120_64\\lib\\gcc\\x86_64-w64-mingw32\\11.2.0\\include\\c++","-isystem","C:\\Qt\\Tools\\mingw1120_64\\lib\\gcc\\x86_64-w64-mingw32\\11.2.0\\include\\c++\\x86_64-w64-mingw32","-isystem","C:\\Qt\\Tools\\mingw1120_64\\lib\\gcc\\x86_64-w64-mingw32\\11.2.0\\include\\c++\\backward","-isystem","C:\\Qt\\Tools\\QtCreator\\bin\\clang\\lib\\clang\\15.0.0\\include","-isystem","C:\\Qt\\Tools\\mingw1120_64\\x86_64-w64-mingw32\\include","-fmessage-length=0","-fdiagnostics-show-note-include-stack","-fretain-comments-from-system-headers","-fmacro-backtrace-limit=0","-ferror-limit=1000","-x","c++-header","D:\\qt\\qt\\STO2\\ui_workshuduleadd.h"],"directory":"D:/qt/qt/STO2/.qtc_clangd","file":"D:/qt/qt/STO2/ui_workshuduleadd.h"},{"arguments":["clang","-Wno-documentation-unknown-command","-Wno-unknown-warning-option","-Wno-unknown-pragmas","-nostdinc","-nostdinc++","-std=gnu++1z","-Wall","-Wextra","-Wextra","-fexceptions","-mthreads","-fsyntax-only","-m64","--target=x86_64-w64-mingw32","-DUNICODE","-D_UNICODE","-DWIN32","-DMINGW_HAS_SECURE_API","-DQT_NO_DEBUG","-DQT_PRINTSUPPORT_LIB","-DQT_CHARTS_LIB","-DQT_OPENGLWIDGETS_LIB","-DQT_WIDGETS_LIB","-DQT_OPENGL_LIB","-DQT_GUI_LIB","-DQT_SQL_LIB","-DQT_CORE_LIB","-DQT_NEEDS_QMAIN","-DQ_CREATOR_RUN","-IC:\\Qt\\Tools\\QtCreator\\share\\qtcreator\\cplusplus\\wrappedMingwHeaders","-IC:\\Qt\\Tools\\QtCreator\\share\\qtcreator\\cplusplus\\wrappedQtHeaders","-IC:\\Qt\\Tools\\QtCreator\\share\\qtcreator\\cplusplus\\wrappedQtHeaders\\QtCore","-ID:\\qt\\qt\\STO2","-IC:\\Qt\\6.4.1\\mingw_64\\include","-IC:\\Qt\\6.4.1\\mingw_64\\include\\QtPrintSupport","-IC:\\Qt\\6.4.1\\mingw_64\\include\\QtCharts","-IC:\\Qt\\6.4.1\\mingw_64\\include\\QtOpenGLWidgets","-IC:\\Qt\\6.4.1\\mingw_64\\include\\QtWidgets","-IC:\\Qt\\6.4.1\\mingw_64\\include\\QtOpenGL","-IC:\\Qt\\6.4.1\\mingw_64\\include\\QtGui","-IC:\\Qt\\6.4.1\\mingw_64\\include\\QtSql","-IC:\\Qt\\6.4.1\\mingw_64\\include\\QtCore","-ID:\\qt\\qt\\STO2\\release","-IC:\\Qt\\6.4.1\\mingw_64\\mkspecs\\win32-g++","-isystem","C:\\Qt\\Tools\\mingw1120_64\\lib\\gcc\\x86_64-w64-mingw32\\11.2.0\\include\\c++","-isystem","C:\\Qt\\Tools\\mingw1120_64\\lib\\gcc\\x86_64-w64-mingw32\\11.2.0\\include\\c++\\x86_64-w64-mingw32","-isystem","C:\\Qt\\Tools\\mingw1120_64\\lib\\gcc\\x86_64-w64-mingw32\\11.2.0\\include\\c++\\backward","-isystem","C:\\Qt\\Tools\\QtCreator\\bin\\clang\\lib\\clang\\15.0.0\\include","-isystem","C:\\Qt\\Tools\\mingw1120_64\\x86_64-w64-mingw32\\include","-fmessage-length=0","-fdiagnostics-show-note-include-stack","-fretain-comments-from-system-headers","-fmacro-backtrace-limit=0","-ferror-limit=1000","-x","c++-header","D:\\qt\\qt\\STO2\\ui_infobase.h"],"directory":"D:/qt/qt/STO2/.qtc_clangd","file":"D:/qt/qt/STO2/ui_infobase.h"},{"arguments":["clang","-Wno-documentation-unknown-command","-Wno-unknown-warning-option","-Wno-unknown-pragmas","-nostdinc","-nostdinc++","-std=gnu++1z","-Wall","-Wextra","-Wextra","-fexceptions","-mthreads","-fsyntax-only","-m64","--target=x86_64-w64-mingw32","-DUNICODE","-D_UNICODE","-DWIN32","-DMINGW_HAS_SECURE_API","-DQT_NO_DEBUG","-DQT_PRINTSUPPORT_LIB","-DQT_CHARTS_LIB","-DQT_OPENGLWIDGETS_LIB","-DQT_WIDGETS_LIB","-DQT_OPENGL_LIB","-DQT_GUI_LIB","-DQT_SQL_LIB","-DQT_CORE_LIB","-DQT_NEEDS_QMAIN","-DQ_CREATOR_RUN","-IC:\\Qt\\Tools\\QtCreator\\share\\qtcreator\\cplusplus\\wrappedMingwHeaders","-IC:\\Qt\\Tools\\QtCreator\\share\\qtcreator\\cplusplus\\wrappedQtHeaders","-IC:\\Qt\\Tools\\QtCreator\\share\\qtcreator\\cplusplus\\wrappedQtHeaders\\QtCore","-ID:\\qt\\qt\\STO2","-IC:\\Qt\\6.4.1\\mingw_64\\include","-IC:\\Qt\\6.4.1\\mingw_64\\include\\QtPrintSupport","-IC:\\Qt\\6.4.1\\mingw_64\\include\\QtCharts","-IC:\\Qt\\6.4.1\\mingw_64\\include\\QtOpenGLWidgets","-IC:\\Qt\\6.4.1\\mingw_64\\include\\QtWidgets","-IC:\\Qt\\6.4.1\\mingw_64\\include\\QtOpenGL","-IC:\\Qt\\6.4.1\\mingw_64\\include\\QtGui","-IC:\\Qt\\6.4.1\\mingw_64\\include\\QtSql","-IC:\\Qt\\6.4.1\\mingw_64\\include\\QtCore","-ID:\\qt\\qt\\STO2\\release","-IC:\\Qt\\6.4.1\\mingw_64\\mkspecs\\win32-g++","-isystem","C:\\Qt\\Tools\\mingw1120_64\\lib\\gcc\\x86_64-w64-mingw32\\11.2.0\\include\\c++","-isystem","C:\\Qt\\Tools\\mingw1120_64\\lib\\gcc\\x86_64-w64-mingw32\\11.2.0\\include\\c++\\x86_64-w64-mingw32","-isystem","C:\\Qt\\Tools\\mingw1120_64\\lib\\gcc\\x86_64-w64-mingw32\\11.2.0\\include\\c++\\backward","-isystem","C:\\Qt\\Tools\\QtCreator\\bin\\clang\\lib\\clang\\15.0.0\\include","-isystem","C:\\Qt\\Tools\\mingw1120_64\\x86_64-w64-mingw32\\include","-fmessage-length=0","-fdiagnostics-show-note-include-stack","-fretain-comments-from-system-headers","-fmacro-backtrace-limit=0","-ferror-limit=1000","-x","c++-header","D:\\qt\\qt\\STO2\\ui_viewtablesto.h"],"directory":"D:/qt/qt/STO2/.qtc_clangd","file":"D:/qt/qt/STO2/ui_viewtablesto.h"},{"arguments":["clang","-Wno-documentation-unknown-command","-Wno-unknown-warning-option","-Wno-unknown-pragmas","-nostdinc","-nostdinc++","-std=gnu++1z","-Wall","-Wextra","-Wextra","-fexceptions","-mthreads","-fsyntax-only","-m64","--target=x86_64-w64-mingw32","-DUNICODE","-D_UNICODE","-DWIN32","-DMINGW_HAS_SECURE_API","-DQT_NO_DEBUG","-DQT_PRINTSUPPORT_LIB","-DQT_CHARTS_LIB","-DQT_OPENGLWIDGETS_LIB","-DQT_WIDGETS_LIB","-DQT_OPENGL_LIB","-DQT_GUI_LIB","-DQT_SQL_LIB","-DQT_CORE_LIB","-DQT_NEEDS_QMAIN","-DQ_CREATOR_RUN","-IC:\\Qt\\Tools\\QtCreator\\share\\qtcreator\\cplusplus\\wrappedMingwHeaders","-IC:\\Qt\\Tools\\QtCreator\\share\\qtcreator\\cplusplus\\wrappedQtHeaders","-IC:\\Qt\\Tools\\QtCreator\\share\\qtcreator\\cplusplus\\wrappedQtHeaders\\QtCore","-ID:\\qt\\qt\\STO2","-IC:\\Qt\\6.4.1\\mingw_64\\include","-IC:\\Qt\\6.4.1\\mingw_64\\include\\QtPrintSupport","-IC:\\Qt\\6.4.1\\mingw_64\\include\\QtCharts","-IC:\\Qt\\6.4.1\\mingw_64\\include\\QtOpenGLWidgets","-IC:\\Qt\\6.4.1\\mingw_64\\include\\QtWidgets","-IC:\\Qt\\6.4.1\\mingw_64\\include\\QtOpenGL","-IC:\\Qt\\6.4.1\\mingw_64\\include\\QtGui","-IC:\\Qt\\6.4.1\\mingw_64\\include\\QtSql","-IC:\\Qt\\6.4.1\\mingw_64\\include\\QtCore","-ID:\\qt\\qt\\STO2\\release","-IC:\\Qt\\6.4.1\\mingw_64\\mkspecs\\win32-g++","-isystem","C:\\Qt\\Tools\\mingw1120_64\\lib\\gcc\\x86_64-w64-mingw32\\11.2.0\\include\\c++","-isystem","C:\\Qt\\Tools\\mingw1120_64\\lib\\gcc\\x86_64-w64-mingw32\\11.2.0\\include\\c++\\x86_64-w64-mingw32","-isystem","C:\\Qt\\Tools\\mingw1120_64\\lib\\gcc\\x86_64-w64-mingw32\\11.2.0\\include\\c++\\backward","-isystem","C:\\Qt\\Tools\\QtCreator\\bin\\clang\\lib\\clang\\15.0.0\\include","-isystem","C:\\Qt\\Tools\\mingw1120_64\\x86_64-w64-mingw32\\include","-fmessage-length=0","-fdiagnostics-show-note-include-stack","-fretain-comments-from-system-headers","-fmacro-backtrace-limit=0","-ferror-limit=1000","-x","c++-header","D:\\qt\\qt\\STO2\\ui_staffadd.h"],"directory":"D:/qt/qt/STO2/.qtc_clangd","file":"D:/qt/qt/STO2/ui_staffadd.h"},{"arguments":["clang","-Wno-documentation-unknown-command","-Wno-unknown-warning-option","-Wno-unknown-pragmas","-nostdinc","-nostdinc++","-std=gnu++1z","-Wall","-Wextra","-Wextra","-fexceptions","-mthreads","-fsyntax-only","-m64","--target=x86_64-w64-mingw32","-DUNICODE","-D_UNICODE","-DWIN32","-DMINGW_HAS_SECURE_API","-DQT_NO_DEBUG","-DQT_PRINTSUPPORT_LIB","-DQT_CHARTS_LIB","-DQT_OPENGLWIDGETS_LIB","-DQT_WIDGETS_LIB","-DQT_OPENGL_LIB","-DQT_GUI_LIB","-DQT_SQL_LIB","-DQT_CORE_LIB","-DQT_NEEDS_QMAIN","-DQ_CREATOR_RUN","-IC:\\Qt\\Tools\\QtCreator\\share\\qtcreator\\cplusplus\\wrappedMingwHeaders","-IC:\\Qt\\Tools\\QtCreator\\share\\qtcreator\\cplusplus\\wrappedQtHeaders","-IC:\\Qt\\Tools\\QtCreator\\share\\qtcreator\\cplusplus\\wrappedQtHeaders\\QtCore","-ID:\\qt\\qt\\STO2","-IC:\\Qt\\6.4.1\\mingw_64\\include","-IC:\\Qt\\6.4.1\\mingw_64\\include\\QtPrintSupport","-IC:\\Qt\\6.4.1\\mingw_64\\include\\QtCharts","-IC:\\Qt\\6.4.1\\mingw_64\\include\\QtOpenGLWidgets","-IC:\\Qt\\6.4.1\\mingw_64\\include\\QtWidgets","-IC:\\Qt\\6.4.1\\mingw_64\\include\\QtOpenGL","-IC:\\Qt\\6.4.1\\mingw_64\\include\\QtGui","-IC:\\Qt\\6.4.1\\mingw_64\\include\\QtSql","-IC:\\Qt\\6.4.1\\mingw_64\\include\\QtCore","-ID:\\qt\\qt\\STO2\\release","-IC:\\Qt\\6.4.1\\mingw_64\\mkspecs\\win32-g++","-isystem","C:\\Qt\\Tools\\mingw1120_64\\lib\\gcc\\x86_64-w64-mingw32\\11.2.0\\include\\c++","-isystem","C:\\Qt\\Tools\\mingw1120_64\\lib\\gcc\\x86_64-w64-mingw32\\11.2.0\\include\\c++\\x86_64-w64-mingw32","-isystem","C:\\Qt\\Tools\\mingw1120_64\\lib\\gcc\\x86_64-w64-mingw32\\11.2.0\\include\\c++\\backward","-isystem","C:\\Qt\\Tools\\QtCreator\\bin\\clang\\lib\\clang\\15.0.0\\include","-isystem","C:\\Qt\\Tools\\mingw1120_64\\x86_64-w64-mingw32\\include","-fmessage-length=0","-fdiagnostics-show-note-include-stack","-fretain-comments-from-system-headers","-fmacro-backtrace-limit=0","-ferror-limit=1000","-x","c++-header","D:\\qt\\qt\\STO2\\ui_ordersadd.h"],"directory":"D:/qt/qt/STO2/.qtc_clangd","file":"D:/qt/qt/STO2/ui_ordersadd.h"},{"arguments":["clang","-Wno-documentation-unknown-command","-Wno-unknown-warning-option","-Wno-unknown-pragmas","-nostdinc","-nostdinc++","-std=gnu++1z","-Wall","-Wextra","-Wextra","-fexceptions","-mthreads","-fsyntax-only","-m64","--target=x86_64-w64-mingw32","-DUNICODE","-D_UNICODE","-DWIN32","-DMINGW_HAS_SECURE_API","-DQT_NO_DEBUG","-DQT_PRINTSUPPORT_LIB","-DQT_CHARTS_LIB","-DQT_OPENGLWIDGETS_LIB","-DQT_WIDGETS_LIB","-DQT_OPENGL_LIB","-DQT_GUI_LIB","-DQT_SQL_LIB","-DQT_CORE_LIB","-DQT_NEEDS_QMAIN","-DQ_CREATOR_RUN","-IC:\\Qt\\Tools\\QtCreator\\share\\qtcreator\\cplusplus\\wrappedMingwHeaders","-IC:\\Qt\\Tools\\QtCreator\\share\\qtcreator\\cplusplus\\wrappedQtHeaders","-IC:\\Qt\\Tools\\QtCreator\\share\\qtcreator\\cplusplus\\wrappedQtHeaders\\QtCore","-ID:\\qt\\qt\\STO2","-IC:\\Qt\\6.4.1\\mingw_64\\include","-IC:\\Qt\\6.4.1\\mingw_64\\include\\QtPrintSupport","-IC:\\Qt\\6.4.1\\mingw_64\\include\\QtCharts","-IC:\\Qt\\6.4.1\\mingw_64\\include\\QtOpenGLWidgets","-IC:\\Qt\\6.4.1\\mingw_64\\include\\QtWidgets","-IC:\\Qt\\6.4.1\\mingw_64\\include\\QtOpenGL","-IC:\\Qt\\6.4.1\\mingw_64\\include\\QtGui","-IC:\\Qt\\6.4.1\\mingw_64\\include\\QtSql","-IC:\\Qt\\6.4.1\\mingw_64\\include\\QtCore","-ID:\\qt\\qt\\STO2\\release","-IC:\\Qt\\6.4.1\\mingw_64\\mkspecs\\win32-g++","-isystem","C:\\Qt\\Tools\\mingw1120_64\\lib\\gcc\\x86_64-w64-mingw32\\11.2.0\\include\\c++","-isystem","C:\\Qt\\Tools\\mingw1120_64\\lib\\gcc\\x86_64-w64-mingw32\\11.2.0\\include\\c++\\x86_64-w64-mingw32","-isystem","C:\\Qt\\Tools\\mingw1120_64\\lib\\gcc\\x86_64-w64-mingw32\\11.2.0\\include\\c++\\backward","-isystem","C:\\Qt\\Tools\\QtCreator\\bin\\clang\\lib\\clang\\15.0.0\\include","-isystem","C:\\Qt\\Tools\\mingw1120_64\\x86_64-w64-mingw32\\include","-fmessage-length=0","-fdiagnostics-show-note-include-stack","-fretain-comments-from-system-headers","-fmacro-backtrace-limit=0","-ferror-limit=1000","-x","c++-header","D:\\qt\\qt\\STO2\\ui_mainwindow.h"],"directory":"D:/qt/qt/STO2/.qtc_clangd","file":"D:/qt/qt/STO2/ui_mainwindow.h"},{"arguments":["clang","-Wno-documentation-unknown-command","-Wno-unknown-warning-option","-Wno-unknown-pragmas","-nostdinc","-nostdinc++","-std=gnu++1z","-Wall","-Wextra","-Wextra","-fexceptions","-mthreads","-fsyntax-only","-m64","--target=x86_64-w64-mingw32","-DUNICODE","-D_UNICODE","-DWIN32","-DMINGW_HAS_SECURE_API","-DQT_NO_DEBUG","-DQT_PRINTSUPPORT_LIB","-DQT_CHARTS_LIB","-DQT_OPENGLWIDGETS_LIB","-DQT_WIDGETS_LIB","-DQT_OPENGL_LIB","-DQT_GUI_LIB","-DQT_SQL_LIB","-DQT_CORE_LIB","-DQT_NEEDS_QMAIN","-DQ_CREATOR_RUN","-IC:\\Qt\\Tools\\QtCreator\\share\\qtcreator\\cplusplus\\wrappedMingwHeaders","-IC:\\Qt\\Tools\\QtCreator\\share\\qtcreator\\cplusplus\\wrappedQtHeaders","-IC:\\Qt\\Tools\\QtCreator\\share\\qtcreator\\cplusplus\\wrappedQtHeaders\\QtCore","-ID:\\qt\\qt\\STO2","-IC:\\Qt\\6.4.1\\mingw_64\\include","-IC:\\Qt\\6.4.1\\mingw_64\\include\\QtPrintSupport","-IC:\\Qt\\6.4.1\\mingw_64\\include\\QtCharts","-IC:\\Qt\\6.4.1\\mingw_64\\include\\QtOpenGLWidgets","-IC:\\Qt\\6.4.1\\mingw_64\\include\\QtWidgets","-IC:\\Qt\\6.4.1\\mingw_64\\include\\QtOpenGL","-IC:\\Qt\\6.4.1\\mingw_64\\include\\QtGui","-IC:\\Qt\\6.4.1\\mingw_64\\include\\QtSql","-IC:\\Qt\\6.4.1\\mingw_64\\include\\QtCore","-ID:\\qt\\qt\\STO2\\release","-IC:\\Qt\\6.4.1\\mingw_64\\mkspecs\\win32-g++","-isystem","C:\\Qt\\Tools\\mingw1120_64\\lib\\gcc\\x86_64-w64-mingw32\\11.2.0\\include\\c++","-isystem","C:\\Qt\\Tools\\mingw1120_64\\lib\\gcc\\x86_64-w64-mingw32\\11.2.0\\include\\c++\\x86_64-w64-mingw32","-isystem","C:\\Qt\\Tools\\mingw1120_64\\lib\\gcc\\x86_64-w64-mingw32\\11.2.0\\include\\c++\\backward","-isystem","C:\\Qt\\Tools\\QtCreator\\bin\\clang\\lib\\clang\\15.0.0\\include","-isystem","C:\\Qt\\Tools\\mingw1120_64\\x86_64-w64-mingw32\\include","-fmessage-length=0","-fdiagnostics-show-note-include-stack","-fretain-comments-from-system-headers","-fmacro-backtrace-limit=0","-ferror-limit=1000","-x","c++-header","D:\\qt\\qt\\STO2\\ui_partsalesadd.h"],"directory":"D:/qt/qt/STO2/.qtc_clangd","file":"D:/qt/qt/STO2/ui_partsalesadd.h"},{"arguments":["clang","-Wno-documentation-unknown-command","-Wno-unknown-warning-option","-Wno-unknown-pragmas","-nostdinc","-nostdinc++","-std=gnu++1z","-Wall","-Wextra","-Wextra","-fexceptions","-mthreads","-fsyntax-only","-m64","--target=x86_64-w64-mingw32","-DUNICODE","-D_UNICODE","-DWIN32","-DMINGW_HAS_SECURE_API","-DQT_NO_DEBUG","-DQT_PRINTSUPPORT_LIB","-DQT_CHARTS_LIB","-DQT_OPENGLWIDGETS_LIB","-DQT_WIDGETS_LIB","-DQT_OPENGL_LIB","-DQT_GUI_LIB","-DQT_SQL_LIB","-DQT_CORE_LIB","-DQT_NEEDS_QMAIN","-DQ_CREATOR_RUN","-IC:\\Qt\\Tools\\QtCreator\\share\\qtcreator\\cplusplus\\wrappedMingwHeaders","-IC:\\Qt\\Tools\\QtCreator\\share\\qtcreator\\cplusplus\\wrappedQtHeaders","-IC:\\Qt\\Tools\\QtCreator\\share\\qtcreator\\cplusplus\\wrappedQtHeaders\\QtCore","-ID:\\qt\\qt\\STO2","-IC:\\Qt\\6.4.1\\mingw_64\\include","-IC:\\Qt\\6.4.1\\mingw_64\\include\\QtPrintSupport","-IC:\\Qt\\6.4.1\\mingw_64\\include\\QtCharts","-IC:\\Qt\\6.4.1\\mingw_64\\include\\QtOpenGLWidgets","-IC:\\Qt\\6.4.1\\mingw_64\\include\\QtWidgets","-IC:\\Qt\\6.4.1\\mingw_64\\include\\QtOpenGL","-IC:\\Qt\\6.4.1\\mingw_64\\include\\QtGui","-IC:\\Qt\\6.4.1\\mingw_64\\include\\QtSql","-IC:\\Qt\\6.4.1\\mingw_64\\include\\QtCore","-ID:\\qt\\qt\\STO2\\release","-IC:\\Qt\\6.4.1\\mingw_64\\mkspecs\\win32-g++","-isystem","C:\\Qt\\Tools\\mingw1120_64\\lib\\gcc\\x86_64-w64-mingw32\\11.2.0\\include\\c++","-isystem","C:\\Qt\\Tools\\mingw1120_64\\lib\\gcc\\x86_64-w64-mingw32\\11.2.0\\include\\c++\\x86_64-w64-mingw32","-isystem","C:\\Qt\\Tools\\mingw1120_64\\lib\\gcc\\x86_64-w64-mingw32\\11.2.0\\include\\c++\\backward","-isystem","C:\\Qt\\Tools\\QtCreator\\bin\\clang\\lib\\clang\\15.0.0\\include","-isystem","C:\\Qt\\Tools\\mingw1120_64\\x86_64-w64-mingw32\\include","-fmessage-length=0","-fdiagnostics-show-note-include-stack","-fretain-comments-from-system-headers","-fmacro-backtrace-limit=0","-ferror-limit=1000","-x","c++-header","D:\\qt\\qt\\STO2\\ui_servicesadd.h"],"directory":"D:/qt/qt/STO2/.qtc_clangd","file":"D:/qt/qt/STO2/ui_servicesadd.h"},{"arguments":["clang","-Wno-documentation-unknown-command","-Wno-unknown-warning-option","-Wno-unknown-pragmas","-nostdinc","-nostdinc++","-std=gnu++1z","-Wall","-Wextra","-Wextra","-fexceptions","-mthreads","-fsyntax-only","-m64","--target=x86_64-w64-mingw32","-DUNICODE","-D_UNICODE","-DWIN32","-DMINGW_HAS_SECURE_API","-DQT_NO_DEBUG","-DQT_PRINTSUPPORT_LIB","-DQT_CHARTS_LIB","-DQT_OPENGLWIDGETS_LIB","-DQT_WIDGETS_LIB","-DQT_OPENGL_LIB","-DQT_GUI_LIB","-DQT_SQL_LIB","-DQT_CORE_LIB","-DQT_NEEDS_QMAIN","-DQ_CREATOR_RUN","-IC:\\Qt\\Tools\\QtCreator\\share\\qtcreator\\cplusplus\\wrappedMingwHeaders","-IC:\\Qt\\Tools\\QtCreator\\share\\qtcreator\\cplusplus\\wrappedQtHeaders","-IC:\\Qt\\Tools\\QtCreator\\share\\qtcreator\\cplusplus\\wrappedQtHeaders\\QtCore","-ID:\\qt\\qt\\STO2","-IC:\\Qt\\6.4.1\\mingw_64\\include","-IC:\\Qt\\6.4.1\\mingw_64\\include\\QtPrintSupport","-IC:\\Qt\\6.4.1\\mingw_64\\include\\QtCharts","-IC:\\Qt\\6.4.1\\mingw_64\\include\\QtOpenGLWidgets","-IC:\\Qt\\6.4.1\\mingw_64\\include\\QtWidgets","-IC:\\Qt\\6.4.1\\mingw_64\\include\\QtOpenGL","-IC:\\Qt\\6.4.1\\mingw_64\\include\\QtGui","-IC:\\Qt\\6.4.1\\mingw_64\\include\\QtSql","-IC:\\Qt\\6.4.1\\mingw_64\\include\\QtCore","-ID:\\qt\\qt\\STO2\\release","-IC:\\Qt\\6.4.1\\mingw_64\\mkspecs\\win32-g++","-isystem","C:\\Qt\\Tools\\mingw1120_64\\lib\\gcc\\x86_64-w64-mingw32\\11.2.0\\include\\c++","-isystem","C:\\Qt\\Tools\\mingw1120_64\\lib\\gcc\\x86_64-w64-mingw32\\11.2.0\\include\\c++\\x86_64-w64-mingw32","-isystem","C:\\Qt\\Tools\\mingw1120_64\\lib\\gcc\\x86_64-w64-mingw32\\11.2.0\\include\\c++\\backward","-isystem","C:\\Qt\\Tools\\QtCreator\\bin\\clang\\lib\\clang\\15.0.0\\include","-isystem","C:\\Qt\\Tools\\mingw1120_64\\x86_64-w64-mingw32\\include","-fmessage-length=0","-fdiagnostics-show-note-include-stack","-fretain-comments-from-system-headers","-fmacro-backtrace-limit=0","-ferror-limit=1000","-x","c++-header","D:\\qt\\qt\\STO2\\ui_warsot.h"],"directory":"D:/qt/qt/STO2/.qtc_clangd","file":"D:/qt/qt/STO2/ui_warsot.h"},{"arguments":["clang","-Wno-documentation-unknown-command","-Wno-unknown-warning-option","-Wno-unknown-pragmas","-nostdinc","-nostdinc++","-std=gnu++1z","-Wall","-Wextra","-Wextra","-fexceptions","-mthreads","-fsyntax-only","-m64","--target=x86_64-w64-mingw32","-DUNICODE","-D_UNICODE","-DWIN32","-DMINGW_HAS_SECURE_API","-DQT_NO_DEBUG","-DQT_PRINTSUPPORT_LIB","-DQT_CHARTS_LIB","-DQT_OPENGLWIDGETS_LIB","-DQT_WIDGETS_LIB","-DQT_OPENGL_LIB","-DQT_GUI_LIB","-DQT_SQL_LIB","-DQT_CORE_LIB","-DQT_NEEDS_QMAIN","-DQ_CREATOR_RUN","-IC:\\Qt\\Tools\\QtCreator\\share\\qtcreator\\cplusplus\\wrappedMingwHeaders","-IC:\\Qt\\Tools\\QtCreator\\share\\qtcreator\\cplusplus\\wrappedQtHeaders","-IC:\\Qt\\Tools\\QtCreator\\share\\qtcreator\\cplusplus\\wrappedQtHeaders\\QtCore","-ID:\\qt\\qt\\STO2","-IC:\\Qt\\6.4.1\\mingw_64\\include","-IC:\\Qt\\6.4.1\\mingw_64\\include\\QtPrintSupport","-IC:\\Qt\\6.4.1\\mingw_64\\include\\QtCharts","-IC:\\Qt\\6.4.1\\mingw_64\\include\\QtOpenGLWidgets","-IC:\\Qt\\6.4.1\\mingw_64\\include\\QtWidgets","-IC:\\Qt\\6.4.1\\mingw_64\\include\\QtOpenGL","-IC:\\Qt\\6.4.1\\mingw_64\\include\\QtGui","-IC:\\Qt\\6.4.1\\mingw_64\\include\\QtSql","-IC:\\Qt\\6.4.1\\mingw_64\\include\\QtCore","-ID:\\qt\\qt\\STO2\\release","-IC:\\Qt\\6.4.1\\mingw_64\\mkspecs\\win32-g++","-isystem","C:\\Qt\\Tools\\mingw1120_64\\lib\\gcc\\x86_64-w64-mingw32\\11.2.0\\include\\c++","-isystem","C:\\Qt\\Tools\\mingw1120_64\\lib\\gcc\\x86_64-w64-mingw32\\11.2.0\\include\\c++\\x86_64-w64-mingw32","-isystem","C:\\Qt\\Tools\\mingw1120_64\\lib\\gcc\\x86_64-w64-mingw32\\11.2.0\\include\\c++\\backward","-isystem","C:\\Qt\\Tools\\QtCreator\\bin\\clang\\lib\\clang\\15.0.0\\include","-isystem","C:\\Qt\\Tools\\mingw1120_64\\x86_64-w64-mingw32\\include","-fmessage-length=0","-fdiagnostics-show-note-include-stack","-fretain-comments-from-system-headers","-fmacro-backtrace-limit=0","-ferror-limit=1000","-x","c++-header","D:\\qt\\qt\\STO2\\ui_sparapartsadd.h"],"directory":"D:/qt/qt/STO2/.qtc_clangd","file":"D:/qt/qt/STO2/ui_sparapartsadd.h"}]